{ "docs": [
{ "a": "e26211idm140592004494432", "t": "Oracle\u00AE Airlines Data Model Implementation and Operations Guide", "h": "toc.htm", 
 "c": [{ "a": "e26211idm140591942222496", "t": "Preface", "h": "preface.htm#DMAOG101", 
 "c": [ { "t": "Audience", "h": "preface.htm#DMAOG102" },
 { "t": "Documentation Accessibility", "h": "preface.htm#DMAOG103" },
 { "t": "Related Oracle Resources", "h": "preface.htm#DMAOG105" },
 { "t": "Conventions", "h": "preface.htm#DMAOG109" },
 { }
 ]
 },
{ "a": "e26211idm140591997266256", "t": "Introduction to Oracle Airlines Data Model Customization", "h": "impintro.htm#DMAOG110", 
 "c": [{ "a": "e26211idm140591990082592", "t": "What is the Oracle Airlines Data Model?", "h": "impintro.htm#DMAOG111", 
 "c": [ { "t": "Components of the Oracle Airlines Data Model", "h": "impintro.htm#DMAOG112" },
 { "t": "Oracle Products That Make Up Oracle Airlines Data Model", "h": "impintro.htm#DMAOG113" },
 { }
 ]
 },
 { "t": "Steps for Implementing an Oracle Airlines Data Model Warehouse", "h": "impintro.htm#DMAOG118" },
{ "a": "e26211idm140591979842688", "t": "Before You Begin Customizing the Oracle Airlines Data Model", "h": "impintro.htm#DMAOG119", 
 "c": [ { "t": "Prerequisite Knowledge for Implementors", "h": "impintro.htm#DMAOG120" },
 { "t": "Responsibilities of a Data Warehouse Governance Committee", "h": "impintro.htm#DMAOG121" },
 { }
 ]
 },
{ "a": "e26211idm140592070313936", "t": "Managing the Metadata for Oracle Airlines Data Model", "h": "impintro.htm#DMAOG124", 
 "c": [ { "t": "Metadata Categories and Standards", "h": "impintro.htm#DMAOG125" },
 { "t": "Working with a Metadata Repository", "h": "impintro.htm#DMAOG126" },
 { "t": "Browsing the Metadata Repository Supplied With Oracle Airlines Data Model", "h": "impintro.htm#DMAOG127" },
 { }
 ]
 },
 { "t": "Performing Fit-Gap Analysis for Oracle Airlines Data Model", "h": "impintro.htm#DMAOG133" },
 { }
 ]
 },
{ "a": "e26211idm140591984645696", "t": "Physical Model Customization", "h": "pdm.htm#DMAOG147", 
 "c": [ { "t": "Characteristics of the Default Physical Model", "h": "pdm.htm#DMAOG148" },
{ "a": "e26211idm140592007841040", "t": "Customizing the Oracle Airlines Data Model Physical Model", "h": "pdm.htm#DMAOG152", 
 "c": [ { "t": "Questions to Answer Before You Customize the Physical Model", "h": "pdm.htm#DMAOG153" },
 { "t": "Conventions When Customizing the Physical Model", "h": "pdm.htm#DMAOG154" },
 { }
 ]
 },
{ "a": "e26211idm140591999594880", "t": "Foundation Layer Customization", "h": "pdm.htm#DMAOG327", 
 "c": [ { "t": "Common Change Scenarios When Customizing the Foundation Layer of Oracle Airlines Data Model", "h": "pdm.htm#DMAOG328" },
 { "t": "Example: Changing the Foundation Layer of the Oracle Airlines Data Model", "h": "pdm.htm#DMAOG347" },
 { }
 ]
 },
{ "a": "e26211idm140592094413904", "t": "General Recommendations When Designing Physical Structures", "h": "pdm.htm#DMAOG157", 
 "c": [ { "t": "Tablespaces in the Oracle Airlines Data Model", "h": "pdm.htm#DMAOG158" },
 { "t": "Data Compression in the Oracle Airlines Data Model", "h": "pdm.htm#DMAOG161" },
 { "t": "Tables for Supertype and Subtype Entities in Oracle Airlines Data Model", "h": "pdm.htm#DMAOG165" },
 { "t": "Surrogate Keys in the Physical Model", "h": "pdm.htm#DMAOG167" },
 { "t": "Integrity Constraints in Oracle Airlines Data Model", "h": "pdm.htm#DMAOG170" },
 { "t": "Indexes and Partitioned Indexes in Oracle Airlines Data Model", "h": "pdm.htm#DMAOG171" },
 { "t": "Partitioned Tables in the Oracle Airlines Data Model", "h": "pdm.htm#DMAOG173" },
 { "t": "Parallel Execution in the Oracle Airlines Data Model", "h": "pdm.htm#DMAOG178" },
 { }
 ]
 },
 { }
 ]
 },
{ "a": "e26211idm140591994326512", "t": "Access Layer Customization", "h": "adm.htm#DMAOG184", 
 "c": [ { "t": "Introduction to Customizing the Access Layer of Oracle Airlines Data Model", "h": "adm.htm#DMAOG185" },
 { "t": "Dimension Tables in the Oracle Airlines Data Model", "h": "adm.htm#DMAOG378" },
{ "a": "e26211idm140591960994240", "t": "Derived Tables in the Oracle Airlines Data Model", "h": "adm.htm#DMAOG186", 
 "c": [ { "t": "Creating New Derived Tables for Calculated Data", "h": "adm.htm#DMAOG187" },
 { "t": "Customizing Data Mining Models in the Oracle Airlines Data Model", "h": "adm.htm#DMAOG188" },
 { }
 ]
 },
 { "t": "Aggregate Tables in the Oracle Airlines Data Model", "h": "adm.htm#DMAOG196" },
{ "a": "e26211idm140591975989216", "t": "Dimensional Components in the Oracle Airlines Data Model", "h": "adm.htm#DMAOG197", 
 "c": [ { "t": "Characteristics of a Dimensional Model", "h": "adm.htm#DMAOG198" },
 { "t": "Characteristics of Relational Star and Snowflake Tables", "h": "adm.htm#DMAOG199" },
 { "t": "Characteristics of the OLAP Dimensional Model", "h": "adm.htm#DMAOG203" },
 { "t": "Characteristics of the OLAP Cubes in Oracle Airlines Data Model", "h": "adm.htm#DMAOG211" },
 { "t": "Defining New Oracle OLAP Cubes for Oracle Airlines Data Model", "h": "adm.htm#DMAOG212" },
 { "t": "Changing an Oracle OLAP Cube in Oracle Airlines Data Model", "h": "adm.htm#DMAOG213" },
 { "t": "Creating a Forecast Cube for Oracle Airlines Data Model", "h": "adm.htm#DMAOG214" },
 { "t": "Choosing a Cube Partitioning Strategy for Oracle Airlines Data Model", "h": "adm.htm#DMAOG215" },
 { "t": "Choosing a Cube Data Maintenance Method for Oracle Airlines Data Model", "h": "adm.htm#DMAOG217" },
 { }
 ]
 },
{ "a": "e26211idm140592094994368", "t": "Materialized Views in the Oracle Airlines Data Model", "h": "adm.htm#DMAOG218", 
 "c": [ { "t": "Types of Materialized Views and Refresh options", "h": "adm.htm#DMAOG219" },
 { "t": "Choosing Indexes for Materialized Views", "h": "adm.htm#DMAOG223" },
 { "t": "Partitioning and Materialized Views", "h": "adm.htm#DMAOG224" },
 { "t": "Compressing Materialized Views", "h": "adm.htm#DMAOG226" },
 { }
 ]
 },
 { }
 ]
 },
{ "a": "e26211idm140592093724144", "t": "ETL Implementation and Customization", "h": "etlmap.htm#DMAOG227", 
 "c": [ { "t": "The Role of ETL in the Oracle Airlines Data Model", "h": "etlmap.htm#DMAOG228" },
{ "a": "e26211idm140591941923616", "t": "ETL for the Foundation Layer of an Oracle Airlines Data Model Warehouse", "h": "etlmap.htm#DMAOG230", 
 "c": [ { "t": "Source-ETL Design Considerations", "h": "etlmap.htm#DMAOG354" },
 { "t": "ETL Architecture for Oracle Airlines Data Model Source-ETL", "h": "etlmap.htm#DMAOG231" },
 { "t": "Creating a Source to Target Mapping Document for the Source-ETL", "h": "etlmap.htm#DMAOG232" },
 { "t": "Designing a Plan for Rectifying Source-ETL Data Quality Problems", "h": "etlmap.htm#DMAOG233" },
 { "t": "Designing Source-ETL Workflow and Jobs Control", "h": "etlmap.htm#DMAOG234" },
 { "t": "Designing Source-ETL Exception Handling", "h": "etlmap.htm#DMAOG235" },
 { "t": "Writing Source-ETL that Loads Efficiently", "h": "etlmap.htm#DMAOG236" },
 { }
 ]
 },
 { "t": "Customizing Intra-ETL for the Oracle Airlines Data Model", "h": "etlmap.htm#DMAOG247" },
{ "a": "e26211idm140591974515264", "t": "Performing an Initial Load of an Oracle Airlines Data Model Warehouse", "h": "etlmap.htm#DMAOG355", 
 "c": [ { "t": "Performing an Initial Load of the Foundation Layer", "h": "etlmap.htm#DMAOG356" },
 { "t": "Performing an Initial Load of the Access Layer", "h": "etlmap.htm#DMAOG249" },
 { }
 ]
 },
{ "a": "e26211idm140592087231920", "t": "Refreshing the Data in an Oracle Airlines Data Model Warehouse", "h": "etlmap.htm#DMAOG357", 
 "c": [ { "t": "Refreshing the Foundation Layer of Oracle Airlines Data Model Warehouse", "h": "etlmap.htm#DMAOG358" },
 { "t": "Refreshing the Access Layer of an Oracle Airlines Data Model Warehouse", "h": "etlmap.htm#DMAOG359" },
 { }
 ]
 },
{ "a": "e26211idm140592000076912", "t": "Managing Errors During Oracle Airlines Data Model Intra-ETL Execution", "h": "etlmap.htm#DMAOG363", 
 "c": [ { "t": "Monitoring the Execution of the Intra-ETL Process", "h": "etlmap.htm#DMAOG364" },
 { "t": "Recovering an Intra ETL Process", "h": "etlmap.htm#DMAOG365" },
 { "t": "Troubleshooting Intra-ETL Performance", "h": "etlmap.htm#DMAOG366" },
 { }
 ]
 },
 { }
 ]
 },
{ "a": "e26211idm140591981489104", "t": "Report and Query Customization", "h": "rep_quer.htm#DMAOG266", 
 "c": [ { "t": "Reporting Approaches in Oracle Airlines Data Model", "h": "rep_quer.htm#DMAOG267" },
 { "t": "Customizing Oracle Airlines Data Model Sample Reports", "h": "rep_quer.htm#DMAOG268" },
 { "t": "Writing Your Own Queries and Reports", "h": "rep_quer.htm#DMAOG269" },
 { "t": "Optimizing Star Queries", "h": "rep_quer.htm#DMAOG271" },
 { "t": "Troubleshooting Oracle Airlines Data Model Report Performance", "h": "rep_quer.htm#DMAOG273" },
{ "a": "e26211idm140591949696224", "t": "Writing As Is and As Was Queries", "h": "rep_quer.htm#DMAOG274", 
 "c": [ { "t": "Characteristics of an As Is Query", "h": "rep_quer.htm#DMAOG344" },
 { "t": "Characteristics of an As Was Query", "h": "rep_quer.htm#DMAOG345" },
 { "t": "Examples: As Is and As Was Queries", "h": "rep_quer.htm#DMAOG346" },
 { }
 ]
 },
 { "t": "Tutorial: Creating a New Oracle Airlines Data Model Dashboard", "h": "rep_quer.htm#DMAOG280" },
 { "t": "Tutorial: Creating a New Oracle Airlines Data Model Report", "h": "rep_quer.htm#DMAOG281" },
 { }
 ]
 },
{ "a": "e26211idm140591992278320", "t": "Sizing and Configuring an Oracle Airlines Data Model Warehouse", "h": "app_size.htm#DMAOG301", 
 "c": [ { "t": "Sizing an Oracle Airlines Data Model Warehouse", "h": "app_size.htm#DMAOG302" },
{ "a": "e26211idm140591960954720", "t": "Configuring a Balanced System for Oracle Airlines Data Model", "h": "app_size.htm#DMAOG305", 
 "c": [ { "t": "Maintaining High Throughput in an Oracle Airlines Data Model Warehouse", "h": "app_size.htm#DMAOG306" },
 { "t": "Configuring I/O in an Oracle Airlines Data Model for Bandwidth not Capacity", "h": "app_size.htm#DMAOG307" },
 { "t": "Planning for Growth of Your Oracle Airlines Data Model", "h": "app_size.htm#DMAOG308" },
 { "t": "Testing the I/O System Before Building the Oracle Airlines Data Model Warehouse", "h": "app_size.htm#DMAOG309" },
 { "t": "Balanced Hardware Configuration Guidelines for Oracle Airlines Data Model", "h": "app_size.htm#DMAOG310" },
 { }
 ]
 },
 { }
 ]
 },
  { }
 ] } ]}