{ "docs": [
{ "a": "e10839idm140591941814400", "t": "Oracle\u00AE Database Administrator's Reference for Linux and UNIX-Based Operating Systems", "h": "toc.htm", 
 "c": [{ "a": "e10839idm140592017728480", "t": "Preface", "h": "preface.htm#UNXAR101", 
 "c": [ { "t": "Audience", "h": "preface.htm#UNXAR102" },
 { "t": "Documentation Accessibility", "h": "preface.htm#UNXAR398" },
 { "t": "Related Documentation", "h": "preface.htm#UNXAR107" },
 { "t": "Conventions", "h": "preface.htm#UNXAR112" },
 { "t": "Command Syntax", "h": "preface.htm#UNXAR113" },
 { "t": "Terminology", "h": "preface.htm#UNXAR114" },
 { "t": "Accessing Documentation", "h": "preface.htm#UNXAR115" },
 { }
 ]
 },
{ "a": "e10839idm140591941705696", "t": "What's New in Oracle Database 11g Release 2 (11.2)", "h": "whatsnew.htm#UNXAR400", 
 "c": [{ "a": "e10839idm140592006478352", "t": "Oracle Database 11g Release 2 (11.2.0.3) New Features", "h": "whatsnew.htm#UNXAR401", 
 "c": [ { "t": "TDE Hardware Acceleration for Oracle Solaris", "h": "whatsnew.htm#UNXAR402" },
 { }
 ]
 },
{ "a": "e10839idm140591991462832", "t": "Oracle Database 11g Release 2 (11.2.0.2) New Features", "h": "whatsnew.htm#UNXAR403", 
 "c": [ { "t": "TDE Hardware Acceleration for Linux", "h": "whatsnew.htm#UNXAR404" },
 { }
 ]
 },
 { }
 ]
 },
{ "a": "e10839idm140591980705392", "t": "Administering Oracle Database", "h": "admin_ora.htm#UNXAR001", 
 "c": [ { "t": "Overview", "h": "admin_ora.htm#UNXAR116" },
{ "a": "e10839idm140592009847104", "t": "Environment Variables", "h": "admin_ora.htm#UNXAR117", 
 "c": [ { "t": "Oracle Database Environment Variables", "h": "admin_ora.htm#UNXAR118" },
 { "t": "UNIX Environment Variables", "h": "admin_ora.htm#UNXAR120" },
 { "t": "Setting a Common Environment", "h": "admin_ora.htm#UNXAR122" },
 { "t": "Setting the System Time Zone", "h": "admin_ora.htm#UNXAR125" },
 { }
 ]
 },
{ "a": "e10839idm140591981255088", "t": "Initialization Parameters", "h": "admin_ora.htm#UNXAR126", 
 "c": [ { "t": "DB_BLOCK_SIZE Initialization Parameter", "h": "admin_ora.htm#UNXAR127" },
 { "t": "ASM_DISKSTRING Initialization Parameter", "h": "admin_ora.htm#UNXAR128" },
 { "t": "LOG_ARCHIVE_DEST_n Initialization Parameter", "h": "admin_ora.htm#UNXAR130" },
 { "t": "DISK_ASYNCH_IO Initialization Parameter (HP-UX)", "h": "admin_ora.htm#UNXAR131" },
 { }
 ]
 },
{ "a": "e10839idm140591999285568", "t": "Operating System Accounts and Groups", "h": "admin_ora.htm#UNXAR132", 
 "c": [ { "t": "Creating Additional Operating System Accounts", "h": "admin_ora.htm#UNXAR133" },
 { "t": "Configuring the Accounts of Oracle Users", "h": "admin_ora.htm#UNXAR134" },
 { }
 ]
 },
 { "t": "Using Trace Files", "h": "admin_ora.htm#UNXAR135" },
 { }
 ]
 },
{ "a": "e10839idm140591977113984", "t": "Stopping and Starting Oracle Software", "h": "strt_stp.htm#UNXAR002", 
 "c": [ { "t": "Oracle Restart", "h": "strt_stp.htm#UNXAR136" },
{ "a": "e10839idm140591983743104", "t": "Stopping and Starting Oracle Processes", "h": "strt_stp.htm#UNXAR138", 
 "c": [ { "t": "Stopping and Starting Oracle Database and Automatic Storage Management Instances", "h": "strt_stp.htm#UNXAR139" },
 { "t": "Stopping and Starting Oracle Restart", "h": "strt_stp.htm#UNXAR142" },
 { "t": "Stopping and Starting Oracle Enterprise Manager Database Control", "h": "strt_stp.htm#UNXAR143" },
 { "t": "Stopping and Starting Oracle Management Agent", "h": "strt_stp.htm#UNXAR146" },
 { }
 ]
 },
 { }
 ]
 },
{ "a": "e10839idm140592005012032", "t": "Configuring Oracle Database", "h": "cnfg_prd.htm#UNXAR003", 
 "c": [{ "a": "e10839idm140592089282880", "t": "Using Configuration Assistants as Standalone Tools", "h": "cnfg_prd.htm#UNXAR149", 
 "c": [ { "t": "Using Oracle Net Configuration Assistant", "h": "cnfg_prd.htm#UNXAR150" },
 { "t": "Using Oracle Database Upgrade Assistant", "h": "cnfg_prd.htm#UNXAR151" },
 { "t": "Using Oracle Database Configuration Assistant", "h": "cnfg_prd.htm#UNXAR152" },
 { "t": "Configuring New or Upgraded Databases", "h": "cnfg_prd.htm#UNXAR153" },
 { }
 ]
 },
 { "t": "Relinking Executables", "h": "cnfg_prd.htm#UNXAR154" },
 { }
 ]
 },
{ "a": "e10839idm140592012564032", "t": "Administering SQL*Plus", "h": "admn_sqlpls.htm#UNXAR004", 
 "c": [{ "a": "e10839idm140591948501328", "t": "Administering Command-Line SQL*Plus", "h": "admn_sqlpls.htm#UNXAR156", 
 "c": [ { "t": "Using Setup Files", "h": "admn_sqlpls.htm#UNXAR157" },
 { "t": "Using the PRODUCT_USER_PROFILE Table", "h": "admn_sqlpls.htm#UNXAR160" },
 { "t": "Using Oracle Database Sample Schemas", "h": "admn_sqlpls.htm#UNXAR161" },
 { "t": "Installing and Removing SQL*Plus Command-Line Help", "h": "admn_sqlpls.htm#UNXAR162" },
 { }
 ]
 },
{ "a": "e10839idm140592014379216", "t": "Using Command-Line SQL*Plus", "h": "admn_sqlpls.htm#UNXAR165", 
 "c": [ { "t": "Using a System Editor from SQL*Plus", "h": "admn_sqlpls.htm#UNXAR166" },
 { "t": "Running Operating System Commands from SQL*Plus", "h": "admn_sqlpls.htm#UNXAR167" },
 { "t": "Interrupting SQL*Plus", "h": "admn_sqlpls.htm#UNXAR168" },
 { "t": "Using the SPOOL Command", "h": "admn_sqlpls.htm#UNXAR169" },
 { }
 ]
 },
{ "a": "e10839idm140592039512224", "t": "SQL*Plus Restrictions", "h": "admn_sqlpls.htm#UNXAR170", 
 "c": [ { "t": "Resizing Windows", "h": "admn_sqlpls.htm#UNXAR171" },
 { "t": "Return Codes", "h": "admn_sqlpls.htm#UNXAR172" },
 { "t": "Hiding the Password", "h": "admn_sqlpls.htm#UNXAR173" },
 { }
 ]
 },
 { }
 ]
 },
{ "a": "e10839idm140592006576784", "t": "Configuring Oracle Net Services", "h": "cnfg_net_srv.htm#UNXAR005", 
 "c": [ { "t": "Locating Oracle Net Services Configuration Files", "h": "cnfg_net_srv.htm#UNXAR174" },
 { "t": "Adapters Utility", "h": "cnfg_net_srv.htm#UNXAR176" },
{ "a": "e10839idm140591981532176", "t": "Oracle Protocol Support", "h": "cnfg_net_srv.htm#UNXAR177", 
 "c": [ { "t": "IPC Protocol Support", "h": "cnfg_net_srv.htm#UNXAR178" },
 { "t": "TCP/IP Protocol Support", "h": "cnfg_net_srv.htm#UNXAR179" },
 { "t": "TCP/IP with Secure Sockets Layer Protocol Support", "h": "cnfg_net_srv.htm#UNXAR180" },
 { }
 ]
 },
 { "t": "Setting Up the Listener for TCP/IP or TCP/IP with Secure Sockets Layer", "h": "cnfg_net_srv.htm#UNXAR181" },
 { }
 ]
 },
{ "a": "e10839idm140591986335712", "t": "Using Oracle Precompilers and the Oracle Call Interface", "h": "prcmp_cll_int.htm#UNXAR006", 
 "c": [{ "a": "e10839idm140592091986848", "t": "Overview of Oracle Precompilers", "h": "prcmp_cll_int.htm#UNXAR183", 
 "c": [ { "t": "Precompiler Configuration Files", "h": "prcmp_cll_int.htm#UNXAR184" },
 { "t": "Relinking Precompiler Executables", "h": "prcmp_cll_int.htm#UNXAR186" },
 { "t": "Precompiler README Files", "h": "prcmp_cll_int.htm#UNXAR188" },
 { "t": "Issues Common to All Precompilers", "h": "prcmp_cll_int.htm#UNXAR190" },
 { "t": "Static and Dynamic Linking", "h": "prcmp_cll_int.htm#UNXAR191" },
 { "t": "Client Shared and Static Libraries", "h": "prcmp_cll_int.htm#UNXAR192" },
 { }
 ]
 },
 { "t": "Bit-Length Support for Client Applications", "h": "prcmp_cll_int.htm#UNXAR194" },
{ "a": "e10839idm140592071605008", "t": "Pro*C/C++ Precompiler", "h": "prcmp_cll_int.htm#UNXAR196", 
 "c": [ { "t": "Pro*C/C++ Demonstration Programs", "h": "prcmp_cll_int.htm#UNXAR197" },
 { "t": "Pro*C/C++ User Programs", "h": "prcmp_cll_int.htm#UNXAR198" },
 { }
 ]
 },
{ "a": "e10839idm140592089164640", "t": "Pro*COBOL Precompiler", "h": "prcmp_cll_int.htm#UNXAR199", 
 "c": [ { "t": "Pro*COBOL Environment Variables", "h": "prcmp_cll_int.htm#UNXAR201" },
 { "t": "Pro*COBOL Oracle Runtime System", "h": "prcmp_cll_int.htm#UNXAR210" },
 { "t": "Pro*COBOL Demonstration Programs", "h": "prcmp_cll_int.htm#UNXAR211" },
 { "t": "Pro*COBOL User Programs", "h": "prcmp_cll_int.htm#UNXAR212" },
 { "t": "FORMAT Precompiler Option", "h": "prcmp_cll_int.htm#UNXAR213" },
 { }
 ]
 },
{ "a": "e10839idm140592088535600", "t": "Pro*FORTRAN Precompiler", "h": "prcmp_cll_int.htm#UNXAR214", 
 "c": [ { "t": "Pro*FORTRAN Demonstration Programs", "h": "prcmp_cll_int.htm#UNXAR215" },
 { "t": "Pro*FORTRAN User Programs", "h": "prcmp_cll_int.htm#UNXAR216" },
 { }
 ]
 },
{ "a": "e10839idm140591977164800", "t": "SQL*Module for ADA", "h": "prcmp_cll_int.htm#UNXAR217", 
 "c": [ { "t": "SQL*Module for Ada Demonstration Programs", "h": "prcmp_cll_int.htm#UNXAR218" },
 { "t": "SQL*Module for Ada User Programs", "h": "prcmp_cll_int.htm#UNXAR219" },
 { }
 ]
 },
{ "a": "e10839idm140591981999392", "t": "OCI and OCCI", "h": "prcmp_cll_int.htm#UNXAR220", 
 "c": [ { "t": "OCI and OCCI Demonstration Programs", "h": "prcmp_cll_int.htm#UNXAR221" },
 { "t": "OCI and OCCI User Programs", "h": "prcmp_cll_int.htm#UNXAR222" },
 { }
 ]
 },
 { "t": "Oracle JDBC/OCI Programs with a 64-Bit Driver", "h": "prcmp_cll_int.htm#UNXAR223" },
 { "t": "Custom Make Files", "h": "prcmp_cll_int.htm#UNXAR224" },
 { "t": "Correcting Undefined Symbols", "h": "prcmp_cll_int.htm#UNXAR225" },
 { "t": "Multithreaded Applications", "h": "prcmp_cll_int.htm#UNXAR226" },
 { "t": "Using Signal Handlers", "h": "prcmp_cll_int.htm#UNXAR227" },
 { "t": "XA Functionality", "h": "prcmp_cll_int.htm#UNXAR231" },
 { }
 ]
 },
{ "a": "e10839idm140591978505616", "t": "SQL*Loader and PL/SQL Demonstrations", "h": "ldr_demo.htm#UNXAR007", 
 "c": [ { "t": "SQL*Loader Demonstrations", "h": "ldr_demo.htm#UNXAR232" },
 { "t": "PL/SQL Demonstrations", "h": "ldr_demo.htm#UNXAR233" },
 { "t": "Calling 32-Bit External Procedures from 64-Bit Oracle Database PL/SQL", "h": "ldr_demo.htm#UNXAR237" },
 { }
 ]
 },
{ "a": "e10839idm140591985590896", "t": "Tuning Oracle Database", "h": "tuning.htm#UNXAR008", 
 "c": [ { "t": "Importance of Tuning", "h": "tuning.htm#UNXAR238" },
{ "a": "e10839idm140591991082384", "t": "Operating System Tools", "h": "tuning.htm#UNXAR239", 
 "c": [ { "t": "vmstat", "h": "tuning.htm#UNXAR240" },
 { "t": "sar", "h": "tuning.htm#UNXAR241" },
 { "t": "iostat", "h": "tuning.htm#UNXAR242" },
 { "t": "swap, swapinfo, swapon, or lsps", "h": "tuning.htm#UNXAR243" },
 { "t": "AIX Tools", "h": "tuning.htm#UNXAR244" },
 { "t": "HP-UX Tools", "h": "tuning.htm#UNXAR248" },
 { "t": "Linux Tools", "h": "tuning.htm#UNXAR249" },
 { "t": "Solaris Tools", "h": "tuning.htm#UNXAR250" },
 { }
 ]
 },
{ "a": "e10839idm140591961009248", "t": "Tuning Memory Management", "h": "tuning.htm#UNXAR251", 
 "c": [ { "t": "Allocating Sufficient Swap Space", "h": "tuning.htm#UNXAR252" },
 { "t": "Controlling Paging", "h": "tuning.htm#UNXAR253" },
 { "t": "Adjusting Oracle Block Size", "h": "tuning.htm#UNXAR254" },
 { "t": "Allocating Memory Resource", "h": "tuning.htm#UNXAR255" },
 { }
 ]
 },
{ "a": "e10839idm140592013861584", "t": "Tuning Disk Input-Output", "h": "tuning.htm#UNXAR256", 
 "c": [ { "t": "Using Automatic Storage Management", "h": "tuning.htm#UNXAR257" },
 { "t": "Choosing the Appropriate File System Type", "h": "tuning.htm#UNXAR258" },
 { }
 ]
 },
{ "a": "e10839idm140592071273552", "t": "Monitoring Disk Performance", "h": "tuning.htm#UNXAR259", 
 "c": [ { "t": "Monitoring Disk Performance on Other Operating Systems", "h": "tuning.htm#UNXAR260" },
 { "t": "Using Disk Resync to Monitor Automatic Storage Management Disk Group", "h": "tuning.htm#UNXAR261" },
 { }
 ]
 },
{ "a": "e10839idm140592021741520", "t": "System Global Area", "h": "tuning.htm#UNXAR262", 
 "c": [ { "t": "Determining the Size of the SGA", "h": "tuning.htm#UNXAR263" },
 { "t": "System Resource Verifier Utility", "h": "tuning.htm#UNXAR405" },
 { "t": "Shared Memory on AIX", "h": "tuning.htm#UNXAR264" },
 { }
 ]
 },
 { "t": "Tuning the Operating System Buffer Cache", "h": "tuning.htm#UNXAR266" },
 { }
 ]
 },
{ "a": "e10839idm140591960289088", "t": "Administering Oracle Database on AIX", "h": "appa_aix.htm#UNXAR009", 
 "c": [{ "a": "e10839idm140592098454624", "t": "Memory and Paging", "h": "appa_aix.htm#UNXAR267", 
 "c": [ { "t": "Controlling Buffer-Cache Paging Activity", "h": "appa_aix.htm#UNXAR268" },
 { "t": "Tuning the AIX File Buffer Cache", "h": "appa_aix.htm#UNXAR269" },
 { "t": "Allocating Sufficient Paging Space", "h": "appa_aix.htm#UNXAR271" },
 { "t": "Controlling Paging", "h": "appa_aix.htm#UNXAR272" },
 { "t": "Setting the Database Block Size", "h": "appa_aix.htm#UNXAR273" },
 { "t": "Tuning the Log Archive Buffers", "h": "appa_aix.htm#UNXAR274" },
 { "t": "Input-Output Buffers and SQL*Loader", "h": "appa_aix.htm#UNXAR275" },
 { }
 ]
 },
{ "a": "e10839idm140592089706896", "t": "Disk Input-Output Issues", "h": "appa_aix.htm#UNXAR277", 
 "c": [ { "t": "AIX Logical Volume Manager", "h": "appa_aix.htm#UNXAR278" },
 { "t": "Using Journaled File Systems Compared to Raw Logical Volumes", "h": "appa_aix.htm#UNXAR281" },
 { "t": "Using Asynchronous Input-Output", "h": "appa_aix.htm#UNXAR287" },
 { "t": "Input-Output Slaves", "h": "appa_aix.htm#UNXAR288" },
 { "t": "Using the DB_FILE_MULTIBLOCK_READ_COUNT Parameter", "h": "appa_aix.htm#UNXAR289" },
 { "t": "Using Write Behind", "h": "appa_aix.htm#UNXAR290" },
 { "t": "Tuning Sequential Read Ahead", "h": "appa_aix.htm#UNXAR291" },
 { "t": "Tuning Disk Input-Output Pacing", "h": "appa_aix.htm#UNXAR292" },
 { "t": "Resilvering with Oracle Database", "h": "appa_aix.htm#UNXAR293" },
 { }
 ]
 },
{ "a": "e10839idm140592007863312", "t": "CPU Scheduling and Process Priorities", "h": "appa_aix.htm#UNXAR295", 
 "c": [ { "t": "Changing Process Running Time Slice", "h": "appa_aix.htm#UNXAR296" },
 { "t": "Using Processor Binding on SMP Systems", "h": "appa_aix.htm#UNXAR297" },
 { }
 ]
 },
 { "t": "Setting the AIXTHREAD_SCOPE Environment Variable", "h": "appa_aix.htm#UNXAR298" },
 { "t": "Network Information Service external naming support", "h": "appa_aix.htm#UNXAR299" },
 { "t": "Simultaneous Multithreading on AIX 5.3 and Later Versions", "h": "appa_aix.htm#UNXAR300" },
 { "t": "Configuring IBM JSSE Provider with Oracle JDBC Thin Driver", "h": "appa_aix.htm#UNXAR301" },
 { }
 ]
 },
{ "a": "e10839idm140591973346832", "t": "Administering Oracle Database on Linux", "h": "appc_linux.htm#UNXAR011", 
 "c": [ { "t": "Extended Buffer Cache Support", "h": "appc_linux.htm#UNXAR321" },
 { "t": "Using HugePages on Linux", "h": "appc_linux.htm#UNXAR327" },
 { "t": "Asynchronous Input-Output Support", "h": "appc_linux.htm#UNXAR328" },
 { "t": "Direct Input-Output Support", "h": "appc_linux.htm#UNXAR330" },
 { "t": "Simultaneous Multithreading", "h": "appc_linux.htm#UNXAR333" },
 { "t": "Allocating Shared Resources", "h": "appc_linux.htm#UNXAR334" },
{ "a": "e10839idm140591983297632", "t": "Database Migration from 32-Bit Linux to 64-Bit Linux", "h": "appc_linux.htm#UNXAR335", 
 "c": [ { "t": "Online Backup of Database With RMAN", "h": "appc_linux.htm#UNXAR336" },
 { "t": "Migrating 32-Bit Linux Database to 64-Bit Linux Database", "h": "appc_linux.htm#UNXAR337" },
 { "t": "Migrating Data To and From ASM", "h": "appc_linux.htm#UNXAR343" },
 { }
 ]
 },
 { }
 ]
 },
{ "a": "e10839idm140591986885056", "t": "Administering Oracle Database on HP-UX", "h": "appb_hpux.htm#UNXAR010", 
 "c": [ { "t": "HP-UX Shared Memory Segments for an Oracle Instance", "h": "appb_hpux.htm#UNXAR302" },
{ "a": "e10839idm140592000665616", "t": "HP-UX SCHED_NOAGE Scheduling Policy", "h": "appb_hpux.htm#UNXAR303", 
 "c": [ { "t": "Enabling SCHED_NOAGE for Oracle Database", "h": "appb_hpux.htm#UNXAR304" },
 { }
 ]
 },
 { "t": "Lightweight Timer Implementation", "h": "appb_hpux.htm#UNXAR305" },
{ "a": "e10839idm140591984406016", "t": "Asynchronous Input-Output", "h": "appb_hpux.htm#UNXAR306", 
 "c": [ { "t": "MLOCK Privilege", "h": "appb_hpux.htm#UNXAR307" },
 { "t": "Implementing Asynchronous Input-Output", "h": "appb_hpux.htm#UNXAR308" },
 { "t": "Verifying Asynchronous Input-Output", "h": "appb_hpux.htm#UNXAR309" },
 { "t": "Asynchronous Flag in SGA", "h": "appb_hpux.htm#UNXAR312" },
 { }
 ]
 },
{ "a": "e10839idm140591984998768", "t": "Large Memory Allocations and Oracle Database Tuning", "h": "appb_hpux.htm#UNXAR313", 
 "c": [ { "t": "Default Large Virtual Memory Page Size", "h": "appb_hpux.htm#UNXAR315" },
 { "t": "Tuning Recommendations", "h": "appb_hpux.htm#UNXAR316" },
 { "t": "Tunable Base Page Size", "h": "appb_hpux.htm#UNXAR317" },
 { }
 ]
 },
 { "t": "CPU_COUNT Initialization Parameter and HP-UX Dynamic Processor Reconfiguration", "h": "appb_hpux.htm#UNXAR318" },
 { "t": "Network Information Service external naming support", "h": "appb_hpux.htm#UNXAR319" },
 { "t": "Activating and Setting Expanded Host Names and Node Names", "h": "appb_hpux.htm#UNXAR320" },
 { }
 ]
 },
{ "a": "e10839idm140592092897536", "t": "Administering Oracle Database on Solaris", "h": "appe_sol.htm#UNXAR013", 
 "c": [ { "t": "Intimate Shared Memory", "h": "appe_sol.htm#UNXAR344" },
 { }
 ]
 },
{ "a": "e10839idm140592048511968", "t": "Using Oracle ODBC Driver", "h": "app_odbc.htm#UNXAR014", 
 "c": [ { "t": "Oracle ODBC Driver Certification", "h": "app_odbc.htm#UNXAR345" },
 { "t": "Features Not Supported", "h": "app_odbc.htm#UNXAR346" },
 { "t": "Implementation of Data Types", "h": "app_odbc.htm#UNXAR347" },
 { "t": "Limitations on Data Types", "h": "app_odbc.htm#UNXAR350" },
 { "t": "Format of the Connection String for the SQLDriverConnect Function", "h": "app_odbc.htm#UNXAR351" },
 { "t": "Reducing Lock Timeout in a Program", "h": "app_odbc.htm#UNXAR352" },
 { "t": "Linking ODBC Applications", "h": "app_odbc.htm#UNXAR353" },
 { "t": "Obtaining Information About ROWIDs", "h": "app_odbc.htm#UNXAR354" },
 { "t": "ROWIDs in a WHERE Clause", "h": "app_odbc.htm#UNXAR355" },
 { "t": "Enabling Result Sets", "h": "app_odbc.htm#UNXAR356" },
 { "t": "Enabling EXEC Syntax", "h": "app_odbc.htm#UNXAR357" },
{ "a": "e10839idm140591993772704", "t": "Supported Functionality", "h": "app_odbc.htm#UNXAR358", 
 "c": [ { "t": "API Conformance", "h": "app_odbc.htm#UNXAR359" },
 { "t": "Implementation of ODBC API Functions", "h": "app_odbc.htm#UNXAR360" },
 { "t": "Implementation of the ODBC SQL Syntax", "h": "app_odbc.htm#UNXAR362" },
 { "t": "Implementation of Data Types", "h": "app_odbc.htm#UNXAR363" },
 { }
 ]
 },
{ "a": "e10839idm140592065424800", "t": "Unicode Support", "h": "app_odbc.htm#UNXAR364", 
 "c": [ { "t": "Unicode Support Within the ODBC Environment", "h": "app_odbc.htm#UNXAR365" },
 { "t": "Unicode Support in ODBC API", "h": "app_odbc.htm#UNXAR366" },
 { "t": "SQLGetData Performance", "h": "app_odbc.htm#UNXAR367" },
 { "t": "Unicode Samples", "h": "app_odbc.htm#UNXAR368" },
 { }
 ]
 },
{ "a": "e10839idm140592015816016", "t": "Performance and Tuning", "h": "app_odbc.htm#UNXAR374", 
 "c": [ { "t": "General ODBC Programming Guidelines", "h": "app_odbc.htm#UNXAR375" },
 { "t": "Data Source Configuration Options", "h": "app_odbc.htm#UNXAR376" },
 { "t": "DATE and TIMESTAMP Data Types", "h": "app_odbc.htm#UNXAR377" },
 { }
 ]
 },
 { "t": "Error Messages", "h": "app_odbc.htm#UNXAR378" },
 { }
 ]
 },
{ "a": "e10839idm140592092579168", "t": "Database Limits", "h": "appg_db_lmts.htm#UNXAR015", 
 "c": [ { "t": "Database Limits", "h": "appg_db_lmts.htm#UNXAR382" },
 { }
 ]
 },
{ "a": "e10839idm140592088074992", "t": "Very Large Memory and HugePages", "h": "appi_vlm.htm#UNXAR385", 
 "c": [{ "a": "e10839idm140592000007344", "t": "Very Large Memory on Linux x86", "h": "appi_vlm.htm#UNXAR386", 
 "c": [ { "t": "Implementing VLM on 32-bit Linux", "h": "appi_vlm.htm#UNXAR387" },
 { "t": "Prerequisites for Implementing VLM", "h": "appi_vlm.htm#UNXAR388" },
 { "t": "Methods To Increase SGA Limits", "h": "appi_vlm.htm#UNXAR389" },
 { "t": "Configuring Very Large Memory for Oracle Database", "h": "appi_vlm.htm#UNXAR392" },
 { "t": "Restrictions Involved in Implementing Very Large Memory", "h": "appi_vlm.htm#UNXAR393" },
 { }
 ]
 },
{ "a": "e10839idm140591948505712", "t": "Overview of HugePages", "h": "appi_vlm.htm#UNXAR394", 
 "c": [ { "t": "Tuning SGA With HugePages", "h": "appi_vlm.htm#UNXAR395" },
 { "t": "Configuring HugePages on Linux", "h": "appi_vlm.htm#UNXAR396" },
 { "t": "Restrictions for HugePages Configurations", "h": "appi_vlm.htm#UNXAR397" },
 { "t": "Disabling Transparent HugePages", "h": "appi_vlm.htm#UNXAR411" },
 { }
 ]
 },
 { }
 ]
 },
 { "t": "Index", "h": "index.htm" },
  { }
 ] } ]}