{ "docs": [
{ "a": "e25609idm140592086894480", "t": "Oracle\u00AE Database Semantic Technologies Developer's Guide", "h": "toc.htm", 
 "c": [{ "a": "e25609idm140592087063216", "t": "Preface", "h": "preface.htm#RDFRM551", 
 "c": [ { "t": "Audience", "h": "preface.htm#RDFRM552" },
 { "t": "Documentation Accessibility", "h": "preface.htm#RDFRM128" },
 { "t": "Related Documents", "h": "preface.htm#RDFRM557" },
 { "t": "Conventions", "h": "preface.htm#RDFRM558" },
 { }
 ]
 },
{ "a": "e25609idm140592039704640", "t": "What's New in Semantic Technologies?", "h": "sdo_rdf_newfeat.htm#RDFRM000", 
 "c": [{ "a": "e25609idm140592098313920", "t": "Release 11.2 Features", "h": "sdo_rdf_newfeat.htm#RDFRM130", 
 "c": [ { "t": "New and Changed Features for Interim Patch for Release11.2.0.3.0", "h": "sdo_rdf_newfeat.htm#RDFRM378" },
 { "t": "Jena Adapter for Oracle Database (Updated November, 2011)", "h": "sdo_rdf_newfeat.htm#RDFRM247" },
 { "t": "Named Graph Support Enhancements (Added in Patch 9825019 in May 2011; Included in Release 11.2.0.3)", "h": "sdo_rdf_newfeat.htm#RDFRM131" },
 { "t": "Spatial Support (Added in Patch 9825019 in May 2011; Included in Release 11.2.0.3)", "h": "sdo_rdf_newfeat.htm#RDFRM132" },
 { "t": "Data Type Indexing (Added in Patch 9825019 in May 2011; Included in Release 11.2.0.3)", "h": "sdo_rdf_newfeat.htm#RDFRM133" },
 { "t": "Jena Adapter SPARQL Gateway Support (Updated September, 2011)", "h": "sdo_rdf_newfeat.htm#RDFRM134" },
 { "t": "Enhanced Optimizer Hint Support in SEM_MATCH (11.2.0.2)", "h": "sdo_rdf_newfeat.htm#RDFRM135" },
 { "t": "Full-Text Indexing and Searching for RDF Terms (11.2.0.2)", "h": "sdo_rdf_newfeat.htm#RDFRM136" },
 { "t": "OLS Triple-Level Security (Added in Patch 9819833 in June 2010)", "h": "sdo_rdf_newfeat.htm#RDFRM137" },
 { "t": "OWL 2 RL Support (Added in Patch 9819833 in June 2010)", "h": "sdo_rdf_newfeat.htm#RDFRM138" },
 { "t": "Features Added in Patch to Release 11.2 (Released March 2010)", "h": "sdo_rdf_newfeat.htm#RDFRM139" },
 { "t": "Sesame Adapter for Oracle Database", "h": "sdo_rdf_newfeat.htm#RDFRM140" },
 { "t": "Semantic Indexing for Documents", "h": "sdo_rdf_newfeat.htm#RDFRM141" },
 { "t": "Virtual Private Database (VPD) and Oracle Label Security (OLS) Support", "h": "sdo_rdf_newfeat.htm#RDFRM142" },
 { "t": "Workspace Manager Support for RDF Data", "h": "sdo_rdf_newfeat.htm#RDFRM143" },
 { "t": "New Procedures to Enable, Downgrade, and Remove Semantic Technologies Support", "h": "sdo_rdf_newfeat.htm#RDFRM144" },
 { "t": "Optimized owl:sameAs Inference", "h": "sdo_rdf_newfeat.htm#RDFRM145" },
 { "t": "Optimizing Entailment Performance Through Compact Structures", "h": "sdo_rdf_newfeat.htm#RDFRM146" },
 { "t": "Incremental Inference", "h": "sdo_rdf_newfeat.htm#RDFRM147" },
 { "t": "Parallel Inference", "h": "sdo_rdf_newfeat.htm#RDFRM148" },
 { "t": "Filter and Union Support in Curly Brace Syntax for SEM_MATCH", "h": "sdo_rdf_newfeat.htm#RDFRM149" },
 { "t": "Simple Knowledge Organization System (SKOS) Support", "h": "sdo_rdf_newfeat.htm#RDFRM150" },
 { "t": "Inference Beyond OWLPrime", "h": "sdo_rdf_newfeat.htm#RDFRM151" },
 { "t": "Systematized Nomenclature of Medicine - Clinical Terms (SNOMED CT) Support", "h": "sdo_rdf_newfeat.htm#RDFRM152" },
 { "t": "New SEM_APIS Package Subprograms", "h": "sdo_rdf_newfeat.htm#RDFRM153" },
 { "t": "Parameters for SEM_PERF.GATHER_STATISTICS", "h": "sdo_rdf_newfeat.htm#RDFRM154" },
 { "t": "SEM_APIS.*_RULES_INDEX Subprograms Deprecated", "h": "sdo_rdf_newfeat.htm#RDFRM155" },
 { }
 ]
 },
{ "a": "e25609idm140592096547728", "t": "Release 11.1 Features", "h": "sdo_rdf_newfeat.htm#RDFRM156", 
 "c": [ { "t": "Features Added for Release 11.1.0.7 (November, 2008)", "h": "sdo_rdf_newfeat.htm#RDFRM157" },
 { "t": "Storage Model Enhancements and Migration", "h": "sdo_rdf_newfeat.htm#RDFRM158" },
 { "t": "Support for OWL Inferencing", "h": "sdo_rdf_newfeat.htm#RDFRM159" },
 { "t": "New Bulk Loading Interface for Improved Performance", "h": "sdo_rdf_newfeat.htm#RDFRM160" },
 { "t": "Ontology-Assisted Querying of Relational Data", "h": "sdo_rdf_newfeat.htm#RDFRM161" },
 { "t": "Required Procedure for Using Semantic Technology Support", "h": "sdo_rdf_newfeat.htm#RDFRM162" },
 { }
 ]
 },
 { }
 ]
 },
{ "a": "e25609idm140592099015232", "t": "Oracle Database Semantic Technologies Overview", "h": "sdo_rdf_concepts.htm#RDFRM100", 
 "c": [ { "t": "Introduction to Oracle Semantic Technologies", "h": "sdo_rdf_concepts.htm#RDFRM560" },
 { "t": "Semantic Data Modeling", "h": "sdo_rdf_concepts.htm#RDFRM562" },
{ "a": "e25609idm140592086319168", "t": "Semantic Data in the Database", "h": "sdo_rdf_concepts.htm#RDFRM563", 
 "c": [ { "t": "Metadata for Models", "h": "sdo_rdf_concepts.htm#RDFRM564" },
 { "t": "Statements", "h": "sdo_rdf_concepts.htm#RDFRM567" },
 { "t": "Subjects and Objects", "h": "sdo_rdf_concepts.htm#RDFRM570" },
 { "t": "Blank Nodes", "h": "sdo_rdf_concepts.htm#RDFRM571" },
 { "t": "Properties", "h": "sdo_rdf_concepts.htm#RDFRM572" },
 { "t": "Inferencing: Rules and Rulebases", "h": "sdo_rdf_concepts.htm#RDFRM573" },
 { "t": "Entailments (Rules Indexes)", "h": "sdo_rdf_concepts.htm#RDFRM579" },
 { "t": "Virtual Models", "h": "sdo_rdf_concepts.htm#RDFRM99894" },
 { "t": "Named Graphs", "h": "sdo_rdf_concepts.htm#RDFRM164" },
 { "t": "Semantic Data Security Considerations", "h": "sdo_rdf_concepts.htm#RDFRM583" },
 { }
 ]
 },
 { "t": "Semantic Metadata Tables and Views", "h": "sdo_rdf_concepts.htm#RDFRM584" },
{ "a": "e25609idm140592080581504", "t": "Semantic Data Types, Constructors, and Methods", "h": "sdo_rdf_concepts.htm#RDFRM586", 
 "c": [ { "t": "Constructors for Inserting Triples", "h": "sdo_rdf_concepts.htm#RDFRM588" },
 { }
 ]
 },
{ "a": "e25609idm140592080249792", "t": "Using the SEM_MATCH Table Function to Query Semantic Data", "h": "sdo_rdf_concepts.htm#RDFRM592", 
 "c": [ { "t": "Performing Queries with Incomplete or Invalid Entailments", "h": "sdo_rdf_concepts.htm#RDFRM595" },
 { "t": "Graph Patterns: Support for Curly Brace Syntax, and OPTIONAL, FILTER, UNION, and GRAPH Keywords", "h": "sdo_rdf_concepts.htm#RDFRM99899" },
 { "t": "Graph Patterns: Support for SPARQL SELECT Syntax", "h": "sdo_rdf_concepts.htm#RDFRM175" },
 { "t": "Inline Query Optimizer Hints", "h": "sdo_rdf_concepts.htm#RDFRM183" },
 { "t": "Full-Text Search", "h": "sdo_rdf_concepts.htm#RDFRM185" },
 { "t": "Spatial Support", "h": "sdo_rdf_concepts.htm#RDFRM187" },
 { "t": "Best Practices for Query Performance", "h": "sdo_rdf_concepts.htm#RDFRM194" },
 { }
 ]
 },
{ "a": "e25609idm140592088416208", "t": "Loading and Exporting Semantic Data", "h": "sdo_rdf_concepts.htm#RDFRM596", 
 "c": [ { "t": "Bulk Loading Semantic Data Using a Staging Table", "h": "sdo_rdf_concepts.htm#RDFRM597" },
 { "t": "Batch Loading N-Triple Format Semantic Data Using the Java API", "h": "sdo_rdf_concepts.htm#RDFRM598" },
 { "t": "Loading Semantic Data Using INSERT Statements", "h": "sdo_rdf_concepts.htm#RDFRM600" },
 { "t": "Exporting Semantic Data", "h": "sdo_rdf_concepts.htm#RDFRM601" },
 { "t": "Purging Unused Values", "h": "sdo_rdf_concepts.htm#RDFRM447" },
 { }
 ]
 },
{ "a": "e25609idm140591944303600", "t": "Using Semantic Network Indexes", "h": "sdo_rdf_concepts.htm#RDFRM99905", 
 "c": [ { "t": "MDSYS.SEM_NETWORK_INDEX_INFO View", "h": "sdo_rdf_concepts.htm#RDFRM207" },
 { }
 ]
 },
 { "t": "Using Data Type Indexes", "h": "sdo_rdf_concepts.htm#RDFRM209" },
 { "t": "Quick Start for Using Semantic Data", "h": "sdo_rdf_concepts.htm#RDFRM602" },
{ "a": "e25609idm140591949403984", "t": "Semantic Data Examples (PL/SQL and Java)", "h": "sdo_rdf_concepts.htm#RDFRM603", 
 "c": [ { "t": "Example: Journal Article Information", "h": "sdo_rdf_concepts.htm#RDFRM604" },
 { "t": "Example: Family Information", "h": "sdo_rdf_concepts.htm#RDFRM606" },
 { }
 ]
 },
 { "t": "Software Naming Changes for Semantic Technologies", "h": "sdo_rdf_concepts.htm#RDFRM612" },
 { "t": "For More Information About Semantic Technologies", "h": "sdo_rdf_concepts.htm#RDFRM213" },
 { }
 ]
 },
{ "a": "e25609idm140592099766592", "t": "OWL Concepts", "h": "owl_concepts.htm#RDFRM200", 
 "c": [{ "a": "e25609idm140592097617712", "t": "Ontologies", "h": "owl_concepts.htm#RDFRM614", 
 "c": [ { "t": "Example: Cancer Ontology", "h": "owl_concepts.htm#RDFRM615" },
 { "t": "Supported OWL Subsets", "h": "owl_concepts.htm#RDFRM618" },
 { }
 ]
 },
{ "a": "e25609idm140592048642816", "t": "Using OWL Inferencing", "h": "owl_concepts.htm#RDFRM620", 
 "c": [ { "t": "Creating a Simple OWL Ontology", "h": "owl_concepts.htm#RDFRM621" },
 { "t": "Performing Native OWL inferencing", "h": "owl_concepts.htm#RDFRM623" },
 { "t": "Performing OWL and User-Defined Rules inferencing", "h": "owl_concepts.htm#RDFRM625" },
 { "t": "Generating OWL inferencing Proofs", "h": "owl_concepts.htm#RDFRM627" },
 { "t": "Validating OWL Models and Entailments", "h": "owl_concepts.htm#RDFRM629" },
 { "t": "Using SEM_APIS.CREATE_ENTAILMENT for RDFS Inference", "h": "owl_concepts.htm#RDFRM631" },
 { "t": "Enhancing Inference Performance", "h": "owl_concepts.htm#RDFRM632" },
 { "t": "Optimizing owl:sameAs Inference", "h": "owl_concepts.htm#RDFRM99906" },
 { "t": "Performing Incremental Inference", "h": "owl_concepts.htm#RDFRM99909" },
 { "t": "Using Parallel Inference", "h": "owl_concepts.htm#RDFRM99910" },
 { "t": "Using Named Graph Based Inferencing (Global and Local)", "h": "owl_concepts.htm#RDFRM214" },
 { "t": "Performing Selective Inferencing (Advanced Information)", "h": "owl_concepts.htm#RDFRM633" },
 { }
 ]
 },
{ "a": "e25609idm140591947768944", "t": "Using Semantic Operators to Query Relational Data", "h": "owl_concepts.htm#RDFRM635", 
 "c": [ { "t": "Using the SEM_RELATED Operator", "h": "owl_concepts.htm#RDFRM636" },
 { "t": "Using the SEM_DISTANCE Ancillary Operator", "h": "owl_concepts.htm#RDFRM638" },
 { "t": "Creating a Semantic Index of Type MDSYS.SEM_INDEXTYPE", "h": "owl_concepts.htm#RDFRM642" },
 { "t": "Using SEM_RELATED and SEM_DISTANCE When the Indexed Column Is Not the First Parameter", "h": "owl_concepts.htm#RDFRM646" },
 { "t": "Using URIPREFIX When Values Are Not Stored as URIs", "h": "owl_concepts.htm#RDFRM647" },
 { }
 ]
 },
 { }
 ]
 },
{ "a": "e25609idm140592096182672", "t": "Simple Knowledge Organization System (SKOS) Support", "h": "skos.htm#RDFRM99911", 
 "c": [{ "a": "e25609idm140592085407008", "t": "Supported and Unsupported SKOS Semantics", "h": "skos.htm#RDFRM99913", 
 "c": [ { "t": "Supported SKOS Semantics", "h": "skos.htm#RDFRM99914" },
 { "t": "Unsupported SKOS Semantics", "h": "skos.htm#RDFRM99915" },
 { }
 ]
 },
{ "a": "e25609idm140592098030608", "t": "Performing Inference on SKOS Models", "h": "skos.htm#RDFRM99916", 
 "c": [ { "t": "Validating SKOS Models and Entailments", "h": "skos.htm#RDFRM99917" },
 { "t": "Property Chain Handling", "h": "skos.htm#RDFRM99919" },
 { }
 ]
 },
 { }
 ]
 },
{ "a": "e25609idm140592086135648", "t": "Semantic Indexing for Documents", "h": "indexing_for_docs.htm#RDFRM99921", 
 "c": [ { "t": "Information Extractors for Semantically Indexing Documents", "h": "indexing_for_docs.htm#RDFRM99922" },
 { "t": "Extractor Policies", "h": "indexing_for_docs.htm#RDFRM99924" },
 { "t": "Semantically Indexing Documents", "h": "indexing_for_docs.htm#RDFRM99925" },
{ "a": "e25609idm140592088657600", "t": "SEM_CONTAINS and Ancillary Operators", "h": "indexing_for_docs.htm#RDFRM220", 
 "c": [ { "t": "SEM_CONTAINS_SELECT Ancillary Operator", "h": "indexing_for_docs.htm#RDFRM221" },
 { "t": "SEM_CONTAINS_COUNT Ancillary Operator", "h": "indexing_for_docs.htm#RDFRM222" },
 { }
 ]
 },
 { "t": "Searching for Documents Using SPARQL Query Patterns", "h": "indexing_for_docs.htm#RDFRM99926" },
 { "t": "Bindings for SPARQL Variables in Matching Subgraphs in a Document (SEM_CONTAINS_SELECT Ancillary Operator)", "h": "indexing_for_docs.htm#RDFRM99927" },
 { "t": "Improving the Quality of Document Search Operations", "h": "indexing_for_docs.htm#RDFRM99928" },
 { "t": "Indexing External Documents", "h": "indexing_for_docs.htm#RDFRM99929" },
 { "t": "Configuring the Calais Extractor type", "h": "indexing_for_docs.htm#RDFRM99930" },
 { "t": "Working with General Architecture for Text Engineering (GATE)", "h": "indexing_for_docs.htm#RDFRM99931" },
 { "t": "Creating a New Extractor Type", "h": "indexing_for_docs.htm#RDFRM99932" },
 { "t": "Creating a Local Semantic Index on a Range-Partitioned Table", "h": "indexing_for_docs.htm#RDFRM223" },
{ "a": "e25609idm140592097699264", "t": "Altering a Semantic Index", "h": "indexing_for_docs.htm#RDFRM224", 
 "c": [ { "t": "Rebuilding Content for All Existing Policies in a Semantic Index", "h": "indexing_for_docs.htm#RDFRM225" },
 { "t": "Rebuilding to Add Content for a New Policy to a Semantic Index", "h": "indexing_for_docs.htm#RDFRM226" },
 { "t": "Rebuilding Content for an Existing Policy from a Semantic Index", "h": "indexing_for_docs.htm#RDFRM227" },
 { "t": "Rebuilding to Drop Content for an Existing Policy from a Semantic Index", "h": "indexing_for_docs.htm#RDFRM228" },
 { }
 ]
 },
 { "t": "Passing Extractor-Specific Parameters in CREATE INDEX and ALTER INDEX", "h": "indexing_for_docs.htm#RDFRM229" },
 { "t": "Performing Document-Centric Inference", "h": "indexing_for_docs.htm#RDFRM230" },
{ "a": "e25609idm140592065306512", "t": "Metadata Views for Semantic Indexing", "h": "indexing_for_docs.htm#RDFRM99933", 
 "c": [ { "t": "MDSYS.RDFCTX_POLICIES View", "h": "indexing_for_docs.htm#RDFRM99934" },
 { "t": "RDFCTX_INDEX_POLICIES View", "h": "indexing_for_docs.htm#RDFRM99936" },
 { "t": "RDFCTX_INDEX_EXCEPTIONS View", "h": "indexing_for_docs.htm#RDFRM99938" },
 { }
 ]
 },
 { "t": "Default Style Sheet for GATE Extractor Output", "h": "indexing_for_docs.htm#RDFRM99940" },
 { }
 ]
 },
{ "a": "e25609idm140592100462992", "t": "Fine-Grained Access Control for RDF Data", "h": "fine_grained_acc.htm#RDFRM99941", 
 "c": [{ "a": "e25609idm140591944215632", "t": "Virtual Private Database (VPD) for RDF Data", "h": "fine_grained_acc.htm#RDFRM99942", 
 "c": [ { "t": "VPD Policy for RDF Data", "h": "fine_grained_acc.htm#RDFRM99943" },
 { "t": "RDF Metadata for Enforcing VPD Policies", "h": "fine_grained_acc.htm#RDFRM99944" },
 { "t": "Data Access Constraints", "h": "fine_grained_acc.htm#RDFRM99945" },
 { "t": "RDFVPD_POLICIES View", "h": "fine_grained_acc.htm#RDFRM99946" },
 { "t": "RDFVPD_MODELS View", "h": "fine_grained_acc.htm#RDFRM99948" },
 { "t": "RDFVPD_POLICY_CONSTRAINTS View", "h": "fine_grained_acc.htm#RDFRM99950" },
 { "t": "RDFVPD_PREDICATE_MDATA View", "h": "fine_grained_acc.htm#RDFRM99952" },
 { "t": "RDFVPD_RESOURCE_REL View", "h": "fine_grained_acc.htm#RDFRM99954" },
 { }
 ]
 },
{ "a": "e25609idm140592087652672", "t": "Oracle Label Security (OLS) for RDF Data", "h": "fine_grained_acc.htm#RDFRM99956", 
 "c": [ { "t": "Triple-Level Security", "h": "fine_grained_acc.htm#RDFRM232" },
 { "t": "Resource-Level Security", "h": "fine_grained_acc.htm#RDFRM233" },
 { }
 ]
 },
 { }
 ]
 },
{ "a": "e25609idm140592086736688", "t": "Workspace Manager Support for RDF Data", "h": "workspace_mgr.htm#RDFRM99965", 
 "c": [{ "a": "e25609idm140592096454448", "t": "Enabling Workspace Manager Support for RDF Data", "h": "workspace_mgr.htm#RDFRM99966", 
 "c": [ { "t": "Removing Workspace Manager Support for RDF Data", "h": "workspace_mgr.htm#RDFRM99967" },
 { }
 ]
 },
 { "t": "Version-Enabling an RDF Model", "h": "workspace_mgr.htm#RDFRM99968" },
 { "t": "Inferring from Version-Enabled RDF Models", "h": "workspace_mgr.htm#RDFRM99969" },
 { "t": "Merging and Refreshing Workspaces in Version-Enabled RDF Models", "h": "workspace_mgr.htm#RDFRM99971" },
 { "t": "Special Considerations When Using Workspace Manager Support for RDF Data", "h": "workspace_mgr.htm#RDFRM472" },
 { "t": "Usage Flow Example: Versioning Semantic Models", "h": "workspace_mgr.htm#RDFRM473" },
 { }
 ]
 },
{ "a": "e25609idm140592088052272", "t": "Jena Adapter for Oracle Database", "h": "sem_jena.htm#RDFRM234", 
 "c": [ { "t": "Setting Up the Software Environment", "h": "sem_jena.htm#RDFRM235" },
{ "a": "e25609idm140592100039200", "t": "Setting Up the SPARQL Service", "h": "sem_jena.htm#RDFRM236", 
 "c": [ { "t": "Creating the Required Data Source Using WebLogic Server", "h": "sem_jena.htm#RDFRM237" },
 { "t": "Configuring the SPARQL Service", "h": "sem_jena.htm#RDFRM238" },
 { "t": "Terminating Long-Running SPARQL Queries", "h": "sem_jena.htm#RDFRM240" },
 { "t": "N-Triples Encoding for Non-ASCII Characters", "h": "sem_jena.htm#RDFRM241" },
 { }
 ]
 },
 { "t": "Setting Up the Semantic Technologies Environment", "h": "sem_jena.htm#RDFRM242" },
 { "t": "SEM_MATCH and Jena Adapter Queries Compared", "h": "sem_jena.htm#RDFRM243" },
{ "a": "e25609idm140591948643184", "t": "Optimized Handling of SPARQL Queries", "h": "sem_jena.htm#RDFRM244", 
 "c": [ { "t": "Compilation of SPARQL queries to a single SEM_MATCH Call", "h": "sem_jena.htm#RDFRM245" },
 { "t": "Optimized Handling of Property Paths", "h": "sem_jena.htm#RDFRM246" },
 { }
 ]
 },
{ "a": "e25609idm140592089018896", "t": "Additions to the SPARQL Syntax to Support Other Features", "h": "sem_jena.htm#RDFRM248", 
 "c": [ { "t": "SQL Hints", "h": "sem_jena.htm#RDFRM249" },
 { "t": "Using Bind Variables in SPARQL Queries", "h": "sem_jena.htm#RDFRM250" },
 { "t": "Additional WHERE Clause Predicates", "h": "sem_jena.htm#RDFRM251" },
 { "t": "Additional Query Options", "h": "sem_jena.htm#RDFRM252" },
 { "t": "Midtier Resource Caching", "h": "sem_jena.htm#RDFRM255" },
 { }
 ]
 },
{ "a": "e25609idm140592098508448", "t": "Functions Supported in SPARQL Queries through the Jena Adapter", "h": "sem_jena.htm#RDFRM256", 
 "c": [ { "t": "Functions in the ARQ Function Library", "h": "sem_jena.htm#RDFRM257" },
 { "t": "Native Oracle Database Functions for Projected Variables", "h": "sem_jena.htm#RDFRM258" },
 { "t": "User-Defined Functions", "h": "sem_jena.htm#RDFRM259" },
 { }
 ]
 },
 { "t": "SPARQL Update Support", "h": "sem_jena.htm#RDFRM476" },
{ "a": "e25609idm140592065261712", "t": "Analytical Functions for RDF Data", "h": "sem_jena.htm#RDFRM479", 
 "c": [ { "t": "Generating Contextual Information about a Path in a Graph", "h": "sem_jena.htm#RDFRM482" },
 { }
 ]
 },
{ "a": "e25609idm140592086650832", "t": "Support for Server-Side APIs", "h": "sem_jena.htm#RDFRM261", 
 "c": [ { "t": "Virtual Models Support", "h": "sem_jena.htm#RDFRM262" },
 { "t": "Connection Pooling Support", "h": "sem_jena.htm#RDFRM263" },
 { "t": "Semantic Model PL/SQL Interfaces", "h": "sem_jena.htm#RDFRM264" },
 { "t": "Inference Options", "h": "sem_jena.htm#RDFRM266" },
 { "t": "PelletInfGraph Class Support Deprecated", "h": "sem_jena.htm#RDFRM267" },
 { }
 ]
 },
{ "a": "e25609idm140591947479952", "t": "Bulk Loading Using the Jena Adapter", "h": "sem_jena.htm#RDFRM268", 
 "c": [ { "t": "Using prepareBulk in Parallel (Multithreaded) Mode", "h": "sem_jena.htm#RDFRM487" },
 { "t": "Handling Illegal Syntax During Data Loading", "h": "sem_jena.htm#RDFRM489" },
 { }
 ]
 },
 { "t": "Automatic Variable Renaming", "h": "sem_jena.htm#RDFRM491" },
 { "t": "JavaScript Object Notation (JSON) Format Support", "h": "sem_jena.htm#RDFRM492" },
{ "a": "e25609idm140592048902976", "t": "Other Recommendations and Guidelines", "h": "sem_jena.htm#RDFRM493", 
 "c": [ { "t": "BOUND or !BOUND Instead of EXISTS or NOT EXISTS", "h": "sem_jena.htm#RDFRM494" },
 { "t": "SPARQL 1.1 SELECT Expressions", "h": "sem_jena.htm#RDFRM495" },
 { "t": "Syntax Involving Bnodes (Blank Nodes)", "h": "sem_jena.htm#RDFRM496" },
 { "t": "Limit in the SERVICE Clause", "h": "sem_jena.htm#RDFRM497" },
 { "t": "OracleGraphWrapperForOntModel Class for Better Performance", "h": "sem_jena.htm#RDFRM498" },
 { }
 ]
 },
{ "a": "e25609idm140592065295824", "t": "Example Queries Using the Jena Adapter", "h": "sem_jena.htm#RDFRM272", 
 "c": [ { "t": "Test.java: Query Family Relationships", "h": "sem_jena.htm#RDFRM273" },
 { "t": "Test6.java: Load OWL Ontology and Perform OWLPrime inference", "h": "sem_jena.htm#RDFRM275" },
 { "t": "Test7.java: Bulk Load OWL Ontology and Perform OWLPrime inference", "h": "sem_jena.htm#RDFRM277" },
 { "t": "Test8.java: SPARQL OPTIONAL Query", "h": "sem_jena.htm#RDFRM279" },
 { "t": "Test9.java: SPARQL Query with LIMIT and OFFSET", "h": "sem_jena.htm#RDFRM281" },
 { "t": "Test10.java: SPARQL Query with TIMEOUT and DOP", "h": "sem_jena.htm#RDFRM283" },
 { "t": "Test11.java: Query Involving Named Graphs", "h": "sem_jena.htm#RDFRM285" },
 { "t": "Test12.java: SPARQL ASK Query", "h": "sem_jena.htm#RDFRM287" },
 { "t": "Test13.java: SPARQL DESCRIBE Query", "h": "sem_jena.htm#RDFRM289" },
 { "t": "Test14.java: SPARQL CONSTRUCT Query", "h": "sem_jena.htm#RDFRM291" },
 { "t": "Test15.java: Query Multiple Models and Specify \"Allow Duplicates\"", "h": "sem_jena.htm#RDFRM293" },
 { "t": "Test16.java: SPARQL Update", "h": "sem_jena.htm#RDFRM295" },
 { "t": "Test17.java: SPARQL Query with ARQ Built-In Functions", "h": "sem_jena.htm#RDFRM297" },
 { "t": "Test18.java: SELECT Cast Query", "h": "sem_jena.htm#RDFRM299" },
 { "t": "Test19.java: Instantiate Oracle Database Using OracleConnection", "h": "sem_jena.htm#RDFRM301" },
 { "t": "Test20.java: Oracle Database Connection Pooling", "h": "sem_jena.htm#RDFRM303" },
 { }
 ]
 },
{ "a": "e25609idm140592087254128", "t": "SPARQL Gateway and Semantic Data", "h": "sem_jena.htm#RDFRM502", 
 "c": [ { "t": "SPARQL Gateway Features and Benefits Overview", "h": "sem_jena.htm#RDFRM503" },
 { "t": "Installing and Configuring SPARQL Gateway", "h": "sem_jena.htm#RDFRM504" },
 { "t": "Using SPARQL Gateway with Semantic Data", "h": "sem_jena.htm#RDFRM510" },
 { "t": "Customizing the Default XSLT File", "h": "sem_jena.htm#RDFRM515" },
 { "t": "Using the SPARQL Gateway Java API", "h": "sem_jena.htm#RDFRM516" },
 { "t": "Using the SPARQL Gateway Graphical Web Interface", "h": "sem_jena.htm#RDFRM520" },
 { "t": "Using SPARQL Gateway as an XML Data Source to OBIEE", "h": "sem_jena.htm#RDFRM532" },
 { }
 ]
 },
 { }
 ]
 },
{ "a": "e25609idm140591949768160", "t": "Sesame Adapter for Oracle Database", "h": "sem_sesame.htm#RDFRM305", 
 "c": [ { "t": "Sesame Adapter Overview", "h": "sem_sesame.htm#RDFRM306" },
{ "a": "e25609idm140592088236016", "t": "Setup and Configuration for the Sesame Adapter", "h": "sem_sesame.htm#RDFRM308", 
 "c": [ { "t": "Setting Up the Software Environment", "h": "sem_sesame.htm#RDFRM309" },
 { "t": "Setting Up the SPARQL Service", "h": "sem_sesame.htm#RDFRM310" },
 { "t": "Setting Up the Semantic Technologies Environment", "h": "sem_sesame.htm#RDFRM314" },
 { }
 ]
 },
 { "t": "SEM_MATCH and Sesame Adapter Queries Compared", "h": "sem_sesame.htm#RDFRM315" },
{ "a": "e25609idm140592099781904", "t": "Optimized Handling of SPARQL Queries", "h": "sem_sesame.htm#RDFRM316", 
 "c": [ { "t": "Compilation of SPARQL Queries to a Single SEM_MATCH Call", "h": "sem_sesame.htm#RDFRM317" },
 { }
 ]
 },
{ "a": "e25609idm140592088181840", "t": "Recommendations for Best Performance", "h": "sem_sesame.htm#RDFRM318", 
 "c": [ { "t": "Statement Storage and Implications for Sesame Adapter Queries", "h": "sem_sesame.htm#RDFRM319" },
 { }
 ]
 },
{ "a": "e25609idm140592100468992", "t": "Additions to the SPARQL Syntax to Support Other Features", "h": "sem_sesame.htm#RDFRM320", 
 "c": [ { "t": "SQL Hints", "h": "sem_sesame.htm#RDFRM321" },
 { "t": "Additional WHERE Clause Predicates", "h": "sem_sesame.htm#RDFRM322" },
 { "t": "Additional Query Options", "h": "sem_sesame.htm#RDFRM323" },
 { }
 ]
 },
{ "a": "e25609idm140592086173504", "t": "Support for Server-Side APIs", "h": "sem_sesame.htm#RDFRM324", 
 "c": [ { "t": "Virtual Models Support", "h": "sem_sesame.htm#RDFRM325" },
 { "t": "Connection Pooling Support", "h": "sem_sesame.htm#RDFRM326" },
 { "t": "Semantic Model PL/SQL Interfaces", "h": "sem_sesame.htm#RDFRM327" },
 { "t": "Inference Options", "h": "sem_sesame.htm#RDFRM329" },
 { }
 ]
 },
{ "a": "e25609idm140591947571504", "t": "Oracle-Specific Extensions to Sesame APIs", "h": "sem_sesame.htm#RDFRM330", 
 "c": [ { "t": "Statement Uniqueness", "h": "sem_sesame.htm#RDFRM331" },
 { "t": "Indexes and Interoperability with the Jena Adapter", "h": "sem_sesame.htm#RDFRM332" },
 { "t": "Inference", "h": "sem_sesame.htm#RDFRM334" },
 { "t": "Performing Analysis Operations", "h": "sem_sesame.htm#RDFRM335" },
 { }
 ]
 },
 { "t": "Using the Sesame Console with the Sesame Adapter", "h": "sem_sesame.htm#RDFRM336" },
{ "a": "e25609idm140592096662192", "t": "Example Queries Using the Sesame Adapter", "h": "sem_sesame.htm#RDFRM338", 
 "c": [ { "t": "Example1.java: Basic Operations", "h": "sem_sesame.htm#RDFRM339" },
 { "t": "Example2.java: Add a Data File (in TRIG format)", "h": "sem_sesame.htm#RDFRM341" },
 { "t": "Example3.java: Simple Query", "h": "sem_sesame.htm#RDFRM343" },
 { "t": "Example4.java: Simple Bulk Load", "h": "sem_sesame.htm#RDFRM345" },
 { "t": "Example5.java: Bulk Load RDF/XML and Application Table Index Maintenance", "h": "sem_sesame.htm#RDFRM347" },
 { "t": "Example6.java: Bulk Load With StatusListener to Handle Loading with Bad Data", "h": "sem_sesame.htm#RDFRM349" },
 { "t": "Example7.java: Load Data from Sesame Store into Oracle Database", "h": "sem_sesame.htm#RDFRM351" },
 { "t": "Example8.java: SPARQL ASK Query", "h": "sem_sesame.htm#RDFRM353" },
 { "t": "Example9.java: SPARQL CONSTRUCT and DESCRIBE", "h": "sem_sesame.htm#RDFRM355" },
 { "t": "Example10.java: Inference", "h": "sem_sesame.htm#RDFRM357" },
 { "t": "Example11.java: Named Graph Query", "h": "sem_sesame.htm#RDFRM359" },
 { "t": "Example12.java: Indexes on Application Table [Advanced]", "h": "sem_sesame.htm#RDFRM361" },
 { "t": "Example13.java: Uniqueness Constraint on Application Table [Advanced]", "h": "sem_sesame.htm#RDFRM363" },
 { "t": "Example14.java: Query Timeout and Parallel Execution [Advanced]", "h": "sem_sesame.htm#RDFRM365" },
 { "t": "Example15.java: Get COUNT of Matches [Advanced]", "h": "sem_sesame.htm#RDFRM367" },
 { "t": "Example16.java: Specify Bind Variable for Constant in Query Pattern [Advanced]", "h": "sem_sesame.htm#RDFRM369" },
 { "t": "Example17.java: Specify Bind Variable for Constant in Different Position in Query Pattern [Advanced]", "h": "sem_sesame.htm#RDFRM371" },
 { "t": "Example18.java: Build URIs from Internal Numeric IDs [Advanced]", "h": "sem_sesame.htm#RDFRM373" },
 { }
 ]
 },
 { }
 ]
 },
{ "a": "e25609idm140591946097952", "t": "SEM_APIS Package Subprograms", "h": "sem_apis_ref.htm#RDFRM500", 
 "c": [ { "t": "SEM_APIS.ADD_DATATYPE_INDEX", "h": "sem_apis_ref.htm#RDFRM382" },
 { "t": "SEM_APIS.ADD_SEM_INDEX", "h": "sem_apis_ref.htm#RDFRM99972" },
 { "t": "SEM_APIS.ALTER_DATATYPE_INDEX", "h": "sem_apis_ref.htm#RDFRM383" },
 { "t": "SEM_APIS.ALTER_ENTAILMENT", "h": "sem_apis_ref.htm#RDFRM99973" },
 { "t": "SEM_APIS.ALTER_MODEL", "h": "sem_apis_ref.htm#RDFRM99974" },
 { "t": "SEM_APIS.ALTER_SEM_INDEX_ON_ENTAILMENT", "h": "sem_apis_ref.htm#RDFRM99975" },
 { "t": "SEM_APIS.ALTER_SEM_INDEX_ON_MODEL", "h": "sem_apis_ref.htm#RDFRM99976" },
 { "t": "SEM_APIS.ANALYZE_ENTAILMENT", "h": "sem_apis_ref.htm#RDFRM650" },
 { "t": "SEM_APIS.ANALYZE_MODEL", "h": "sem_apis_ref.htm#RDFRM649" },
 { "t": "SEM_APIS.BULK_LOAD_FROM_STAGING_TABLE", "h": "sem_apis_ref.htm#RDFRM651" },
 { "t": "SEM_APIS.CLEANUP_FAILED", "h": "sem_apis_ref.htm#RDFRM652" },
 { "t": "SEM_APIS.COMPOSE_RDF_TERM", "h": "sem_apis_ref.htm#RDFRM99978" },
 { "t": "SEM_APIS.CREATE_ENTAILMENT", "h": "sem_apis_ref.htm#RDFRM653" },
 { "t": "SEM_APIS.CREATE_RULEBASE", "h": "sem_apis_ref.htm#RDFRM655" },
 { "t": "SEM_APIS.CREATE_SEM_MODEL", "h": "sem_apis_ref.htm#RDFRM657" },
 { "t": "SEM_APIS.CREATE_SEM_NETWORK", "h": "sem_apis_ref.htm#RDFRM658" },
 { "t": "SEM_APIS.CREATE_SOURCE_EXTERNAL_TABLE", "h": "sem_apis_ref.htm#RDFRM384" },
 { "t": "SEM_APIS.CREATE_VIRTUAL_MODEL", "h": "sem_apis_ref.htm#RDFRM99982" },
 { "t": "SEM_APIS.DISABLE_CHANGE_TRACKING", "h": "sem_apis_ref.htm#RDFRM99983" },
 { "t": "SEM_APIS.DISABLE_INC_INFERENCE", "h": "sem_apis_ref.htm#RDFRM99984" },
 { "t": "SEM_APIS.DROP_DATATYPE_INDEX", "h": "sem_apis_ref.htm#RDFRM385" },
 { "t": "SEM_APIS.DROP_ENTAILMENT", "h": "sem_apis_ref.htm#RDFRM659" },
 { "t": "SEM_APIS.DROP_RULEBASE", "h": "sem_apis_ref.htm#RDFRM660" },
 { "t": "SEM_APIS.DROP_SEM_INDEX", "h": "sem_apis_ref.htm#RDFRM99985" },
 { "t": "SEM_APIS.DROP_SEM_MODEL", "h": "sem_apis_ref.htm#RDFRM662" },
 { "t": "SEM_APIS.DROP_SEM_NETWORK", "h": "sem_apis_ref.htm#RDFRM663" },
 { "t": "SEM_APIS.DROP_USER_INFERENCE_OBJS", "h": "sem_apis_ref.htm#RDFRM664" },
 { "t": "SEM_APIS.DROP_VIRTUAL_MODEL", "h": "sem_apis_ref.htm#RDFRM99986" },
 { "t": "SEM_APIS.ENABLE_CHANGE_TRACKING", "h": "sem_apis_ref.htm#RDFRM99987" },
 { "t": "SEM_APIS.ENABLE_INC_INFERENCE", "h": "sem_apis_ref.htm#RDFRM99988" },
 { "t": "SEM_APIS.ESCAPE_CLOB_TERM", "h": "sem_apis_ref.htm#RDFRM449" },
 { "t": "SEM_APIS.ESCAPE_CLOB_VALUE", "h": "sem_apis_ref.htm#RDFRM450" },
 { "t": "SEM_APIS.ESCAPE_RDF_TERM", "h": "sem_apis_ref.htm#RDFRM451" },
 { "t": "SEM_APIS.ESCAPE_RDF_VALUE", "h": "sem_apis_ref.htm#RDFRM452" },
 { "t": "SEM_APIS.GET_CHANGE_TRACKING_INFO", "h": "sem_apis_ref.htm#RDFRM386" },
 { "t": "SEM_APIS.GET_INC_INF_INFO", "h": "sem_apis_ref.htm#RDFRM387" },
 { "t": "SEM_APIS.GET_MODEL_ID", "h": "sem_apis_ref.htm#RDFRM665" },
 { "t": "SEM_APIS.GET_MODEL_NAME", "h": "sem_apis_ref.htm#RDFRM666" },
 { "t": "SEM_APIS.GET_TRIPLE_ID", "h": "sem_apis_ref.htm#RDFRM667" },
 { "t": "SEM_APIS.GETV$DATETIMETZVAL", "h": "sem_apis_ref.htm#RDFRM388" },
 { "t": "SEM_APIS.GETV$DATETZVAL", "h": "sem_apis_ref.htm#RDFRM389" },
 { "t": "SEM_APIS.GETV$NUMERICVAL", "h": "sem_apis_ref.htm#RDFRM390" },
 { "t": "SEM_APIS.GETV$STRINGVAL", "h": "sem_apis_ref.htm#RDFRM391" },
 { "t": "SEM_APIS.GETV$TIMETZVAL", "h": "sem_apis_ref.htm#RDFRM392" },
 { "t": "SEM_APIS.IS_TRIPLE", "h": "sem_apis_ref.htm#RDFRM668" },
 { "t": "SEM_APIS.LOAD_INTO_STAGING_TABLE", "h": "sem_apis_ref.htm#RDFRM393" },
 { "t": "SEM_APIS.LOOKUP_ENTAILMENT", "h": "sem_apis_ref.htm#RDFRM669" },
 { "t": "SEM_APIS.MERGE_MODELS", "h": "sem_apis_ref.htm#RDFRM99989" },
 { "t": "SEM_APIS.PRIVILEGE_ON_APP_TABLES", "h": "sem_apis_ref.htm#RDFRM453" },
 { "t": "SEM_APIS.PURGE_UNUSED_VALUES", "h": "sem_apis_ref.htm#RDFRM454" },
 { "t": "SEM_APIS.REFRESH_SEM_NETWORK_INDEX_INFO", "h": "sem_apis_ref.htm#RDFRM394" },
 { "t": "SEM_APIS.REMOVE_DUPLICATES", "h": "sem_apis_ref.htm#RDFRM99990" },
 { "t": "SEM_APIS.RENAME_ENTAILMENT", "h": "sem_apis_ref.htm#RDFRM99991" },
 { "t": "SEM_APIS.RENAME_MODEL", "h": "sem_apis_ref.htm#RDFRM99992" },
 { "t": "SEM_APIS.SWAP_NAMES", "h": "sem_apis_ref.htm#RDFRM99993" },
 { "t": "SEM_APIS.UNESCAPE_CLOB_TERM", "h": "sem_apis_ref.htm#RDFRM455" },
 { "t": "SEM_APIS.UNESCAPE_CLOB_VALUE", "h": "sem_apis_ref.htm#RDFRM456" },
 { "t": "SEM_APIS.UNESCAPE_RDF_TERM", "h": "sem_apis_ref.htm#RDFRM457" },
 { "t": "SEM_APIS.UNESCAPE_RDF_VALUE", "h": "sem_apis_ref.htm#RDFRM458" },
 { "t": "SEM_APIS.VALIDATE_ENTAILMENT", "h": "sem_apis_ref.htm#RDFRM670" },
 { "t": "SEM_APIS.VALIDATE_MODEL", "h": "sem_apis_ref.htm#RDFRM671" },
 { "t": "SEM_APIS.VALUE_NAME_PREFIX", "h": "sem_apis_ref.htm#RDFRM672" },
 { "t": "SEM_APIS.VALUE_NAME_SUFFIX", "h": "sem_apis_ref.htm#RDFRM673" },
 { }
 ]
 },
{ "a": "e25609idm140592097251456", "t": "SEM_OLS Package Subprograms", "h": "sem_ols_ref.htm#RDFRM395", 
 "c": [ { "t": "SEM_OLS.APPLY_POLICY_TO_APP_TAB", "h": "sem_ols_ref.htm#RDFRM396" },
 { "t": "SEM_OLS.REMOVE_POLICY_FROM_APP_TAB", "h": "sem_ols_ref.htm#RDFRM397" },
 { }
 ]
 },
{ "a": "e25609idm140592098459328", "t": "SEM_PERF Package Subprograms", "h": "sem_perf_ref.htm#RDFRM550", 
 "c": [ { "t": "SEM_PERF.GATHER_STATS", "h": "sem_perf_ref.htm#RDFRM674" },
 { }
 ]
 },
{ "a": "e25609idm140592088144912", "t": "SEM_RDFCTX Package Subprograms", "h": "sem_rdfctx_ref.htm#RDFRM800", 
 "c": [ { "t": "SEM_RDFCTX.ADD_DEPENDENT_POLICY", "h": "sem_rdfctx_ref.htm#RDFRM536" },
 { "t": "SEM_RDFCTX.CREATE_POLICY", "h": "sem_rdfctx_ref.htm#RDFRM99994" },
 { "t": "SEM_RDFCTX.DROP_POLICY", "h": "sem_rdfctx_ref.htm#RDFRM99995" },
 { "t": "SEM_RDFCTX.MAINTAIN_TRIPLES", "h": "sem_rdfctx_ref.htm#RDFRM99996" },
 { "t": "SEM_RDFCTX.SET_DEFAULT_POLICY", "h": "sem_rdfctx_ref.htm#RDFRM99997" },
 { "t": "SEM_RDFCTX.SET_EXTRACTOR_PARAM", "h": "sem_rdfctx_ref.htm#RDFRM99998" },
 { }
 ]
 },
{ "a": "e25609idm140592087183280", "t": "SEM_RDFSA Package Subprograms", "h": "sem_rdfsa_ref.htm#RDFRM99999", 
 "c": [ { "t": "SEM_RDFSA.ADD_VPD_CONSTRAINT", "h": "sem_rdfsa_ref.htm#RDFRM101" },
 { "t": "SEM_RDFSA.APPLY_OLS_POLICY", "h": "sem_rdfsa_ref.htm#RDFRM102" },
 { "t": "SEM_RDFSA.APPLY_VPD_POLICY", "h": "sem_rdfsa_ref.htm#RDFRM104" },
 { "t": "SEM_RDFSA.CREATE_VPD_POLICY", "h": "sem_rdfsa_ref.htm#RDFRM105" },
 { "t": "SEM_RDFSA.DELETE_VPD_CONSTRAINT", "h": "sem_rdfsa_ref.htm#RDFRM106" },
 { "t": "SEM_RDFSA.DISABLE_OLS_POLICY", "h": "sem_rdfsa_ref.htm#RDFRM107" },
 { "t": "SEM_RDFSA.DROP_VPD_POLICY", "h": "sem_rdfsa_ref.htm#RDFRM108" },
 { "t": "SEM_RDFSA.ENABLE_OLS_POLICY", "h": "sem_rdfsa_ref.htm#RDFRM109" },
 { "t": "SEM_RDFSA.MAINT_VPD_METADATA", "h": "sem_rdfsa_ref.htm#RDFRM110" },
 { "t": "SEM_RDFSA.REMOVE_OLS_POLICY", "h": "sem_rdfsa_ref.htm#RDFRM111" },
 { "t": "SEM_RDFSA.REMOVE_VPD_POLICY", "h": "sem_rdfsa_ref.htm#RDFRM112" },
 { "t": "SEM_RDFSA.RESET_MODEL_LABELS", "h": "sem_rdfsa_ref.htm#RDFRM113" },
 { "t": "SEM_RDFSA.SET_PREDICATE_LABEL", "h": "sem_rdfsa_ref.htm#RDFRM114" },
 { "t": "SEM_RDFSA.SET_RDFS_LABEL", "h": "sem_rdfsa_ref.htm#RDFRM115" },
 { "t": "SEM_RDFSA.SET_RESOURCE_LABEL", "h": "sem_rdfsa_ref.htm#RDFRM116" },
 { "t": "SEM_RDFSA.SET_RULE_LABEL", "h": "sem_rdfsa_ref.htm#RDFRM117" },
 { }
 ]
 },
{ "a": "e25609idm140591946999136", "t": "Enabling, Downgrading, or Removing Semantic Technologies Support", "h": "sem_enable.htm#RDFRM118", 
 "c": [{ "a": "e25609idm140592087684992", "t": "Enabling Semantic Technologies Support", "h": "sem_enable.htm#RDFRM119", 
 "c": [ { "t": "Enabling Semantic Technologies Support in a New Database Installation", "h": "sem_enable.htm#RDFRM120" },
 { "t": "Upgrading Semantic Technologies Support from Release 11.1", "h": "sem_enable.htm#RDFRM121" },
 { "t": "Upgrading Semantic Technologies Support from Release 10.2", "h": "sem_enable.htm#RDFRM122" },
 { "t": "Release 11.2.0.2: Required Actions if Semantic Technologies Installation is Invalid", "h": "sem_enable.htm#RDFRM399" },
 { "t": "Spatial and Partitioning Requirements", "h": "sem_enable.htm#RDFRM123" },
 { }
 ]
 },
{ "a": "e25609idm140591947969536", "t": "Downgrading Semantic Technologies Support to a Previous Release", "h": "sem_enable.htm#RDFRM124", 
 "c": [ { "t": "Downgrading to Release 11.1 Semantic Technologies Support", "h": "sem_enable.htm#RDFRM125" },
 { "t": "Downgrading to Release 10.2 Semantic Technologies Support", "h": "sem_enable.htm#RDFRM126" },
 { }
 ]
 },
 { "t": "Removing Semantic Technologies Support", "h": "sem_enable.htm#RDFRM127" },
 { }
 ]
 },
{ "a": "e25609idm140592089213984", "t": "SEM_MATCH Support for Spatial Queries", "h": "sem_spatial_orageo.htm#RDFRM400", 
 "c": [ { "t": "orageo:area", "h": "sem_spatial_orageo.htm#RDFRM401" },
 { "t": "orageo:buffer", "h": "sem_spatial_orageo.htm#RDFRM402" },
 { "t": "orageo:centroid", "h": "sem_spatial_orageo.htm#RDFRM403" },
 { "t": "orageo:convexHull", "h": "sem_spatial_orageo.htm#RDFRM404" },
 { "t": "orageo:difference", "h": "sem_spatial_orageo.htm#RDFRM405" },
 { "t": "orageo:distance", "h": "sem_spatial_orageo.htm#RDFRM406" },
 { "t": "orageo:intersection", "h": "sem_spatial_orageo.htm#RDFRM407" },
 { "t": "orageo:length", "h": "sem_spatial_orageo.htm#RDFRM408" },
 { "t": "orageo:mbr", "h": "sem_spatial_orageo.htm#RDFRM409" },
 { "t": "orageo:nearestNeighbor", "h": "sem_spatial_orageo.htm#RDFRM410" },
 { "t": "orageo:relate", "h": "sem_spatial_orageo.htm#RDFRM411" },
 { "t": "orageo:union", "h": "sem_spatial_orageo.htm#RDFRM412" },
 { "t": "orageo:withinDistance", "h": "sem_spatial_orageo.htm#RDFRM413" },
 { "t": "orageo:xor", "h": "sem_spatial_orageo.htm#RDFRM414" },
 { }
 ]
 },
 { "t": "Glossary", "h": "sem_glossary.htm#RDFRM415" },
  { }
 ] } ]}