{ "docs": [
{ "a": "e10642idm140592021910128", "t": "Oracle\u00AE Database Backup and Recovery User's Guide", "h": "toc.htm", 
 "c": [{ "a": "e10642idm140591990251328", "t": "Preface", "h": "preface.htm#BRADV1102", 
 "c": [ { "t": "Audience", "h": "preface.htm#BRADV102" },
 { "t": "Documentation Accessibility", "h": "preface.htm#BABBCEHA" },
 { "t": "Related Documentation", "h": "preface.htm#BRADV1111" },
 { "t": "Relocated Documentation", "h": "preface.htm#BRADV527" },
 { "t": "Conventions", "h": "preface.htm#BRADV112" },
 { }
 ]
 },
{ "a": "e10642idm140592009412096", "t": "What's New in Backup and Recovery?", "h": "wnbradv.htm#BRADV021", 
 "c": [{ "a": "e10642idm140592003886608", "t": "New Backup and Recovery Features for Oracle 11g Release 2", "h": "wnbradv.htm#BRADV1113", 
 "c": [ { "t": "Changes in RMAN Functionality or Prerequisites", "h": "wnbradv.htm#BRADV542" },
 { }
 ]
 },
 { }
 ]
 },
{ "a": "e10642idm140591942473632", "t": "Introduction to Backup and Recovery", "h": "rcmintro.htm#BRADV8001", 
 "c": [{ "a": "e10642idm140591999077280", "t": "Purpose of Backup and Recovery", "h": "rcmintro.htm#BRADV89334", 
 "c": [ { "t": "Data Protection", "h": "rcmintro.htm#BRADV89335" },
 { "t": "Data Preservation", "h": "rcmintro.htm#BRADV89339" },
 { "t": "Data Transfer", "h": "rcmintro.htm#BRADV89340" },
 { }
 ]
 },
 { "t": "Oracle Backup and Recovery Solutions", "h": "rcmintro.htm#BRADV89341" },
{ "a": "e10642idm140591983189328", "t": "Oracle Flashback Technology", "h": "rcmintro.htm#BRADV89342", 
 "c": [ { "t": "Logical Flashback Features", "h": "rcmintro.htm#BRADV89343" },
 { "t": "Flashback Database", "h": "rcmintro.htm#BRADV89344" },
 { }
 ]
 },
 { "t": "Data Recovery Advisor", "h": "rcmintro.htm#BRADV89345" },
{ "a": "e10642idm140591990039552", "t": "Backup and Recovery Documentation Roadmap", "h": "rcmintro.htm#BRADV99997", 
 "c": [ { "t": "Recovery Manager Documentation Roadmap", "h": "rcmintro.htm#BRADV99998" },
 { "t": "User-Managed Backup and Recovery Documentation Roadmap", "h": "rcmintro.htm#BRADV99999" },
 { }
 ]
 },
 { }
 ]
 },
{ "a": "e10642idm140591993023136", "t": "Getting Started with RMAN", "h": "rcmquick.htm#BRADV89346", 
 "c": [ { "t": "Overview of the RMAN Environment", "h": "rcmquick.htm#BRADV89347" },
 { "t": "Starting RMAN and Connecting to a Database", "h": "rcmquick.htm#BRADV89348" },
 { "t": "Showing the Default RMAN Configuration", "h": "rcmquick.htm#BRADV89349" },
{ "a": "e10642idm140592094104592", "t": "Backing Up a Database", "h": "rcmquick.htm#BRADV89350", 
 "c": [ { "t": "Backing Up a Database in ARCHIVELOG Mode", "h": "rcmquick.htm#BRADV90058" },
 { "t": "Backing Up a Database in NOARCHIVELOG Mode", "h": "rcmquick.htm#BRADV90059" },
 { "t": "Typical Backup Options", "h": "rcmquick.htm#BRADV89352" },
 { "t": "Making Incremental Backups", "h": "rcmquick.htm#BRADV89353" },
 { "t": "Validating Database Files and Backups", "h": "rcmquick.htm#BRADV89355" },
 { "t": "Scripting RMAN Operations", "h": "rcmquick.htm#BRADV89356" },
 { }
 ]
 },
{ "a": "e10642idm140591974429184", "t": "Reporting on RMAN Operations", "h": "rcmquick.htm#BRADV89357", 
 "c": [ { "t": "Listing Backups", "h": "rcmquick.htm#BRADV89358" },
 { "t": "Reporting on Database Files and Backups", "h": "rcmquick.htm#BRADV89359" },
 { }
 ]
 },
{ "a": "e10642idm140591995407904", "t": "Maintaining RMAN Backups", "h": "rcmquick.htm#BRADV89360", 
 "c": [ { "t": "Cross-checking Backups", "h": "rcmquick.htm#BRADV89362" },
 { "t": "Deleting Obsolete Backups", "h": "rcmquick.htm#BRADV89363" },
 { }
 ]
 },
{ "a": "e10642idm140592071812240", "t": "Diagnosing and Repairing Failures with Data Recovery Advisor", "h": "rcmquick.htm#BRADV89364", 
 "c": [ { "t": "Listing Failures and Determining Repair Options", "h": "rcmquick.htm#BRADV89365" },
 { "t": "Repairing Failures", "h": "rcmquick.htm#BRADV89366" },
 { }
 ]
 },
 { "t": "Rewinding a Database with Flashback Database", "h": "rcmquick.htm#BRADV89367" },
{ "a": "e10642idm140592022161520", "t": "Restoring and Recovering Database Files", "h": "rcmquick.htm#BRADV89368", 
 "c": [ { "t": "Preparing to Restore and Recover Database Files", "h": "rcmquick.htm#BRADV99956" },
 { "t": "Recovering the Whole Database", "h": "rcmquick.htm#BRADV89369" },
 { "t": "Recovering Tablespaces", "h": "rcmquick.htm#BRADV89370" },
 { "t": "Recovering Individual Data Blocks", "h": "rcmquick.htm#BRADV89371" },
 { }
 ]
 },
 { }
 ]
 },
{ "a": "e10642idm140591995761280", "t": "Recovery Manager Architecture", "h": "rcmarchi.htm#BRADV001", 
 "c": [ { "t": "About the RMAN Environment", "h": "rcmarchi.htm#BRADV101" },
 { "t": "RMAN Command-Line Client", "h": "rcmarchi.htm#BRADV1002" },
{ "a": "e10642idm140591988518848", "t": "RMAN Channels", "h": "rcmarchi.htm#BRADV105", 
 "c": [ { "t": "Channels and Devices", "h": "rcmarchi.htm#BRADV89373" },
 { "t": "Automatic and Manual Channels", "h": "rcmarchi.htm#BRADV89374" },
 { }
 ]
 },
 { "t": "RMAN Repository", "h": "rcmarchi.htm#BRADV103" },
{ "a": "e10642idm140591990377088", "t": "Media Management", "h": "rcmarchi.htm#BRADV104", 
 "c": [ { "t": "RMAN Interaction with a Media Manager", "h": "rcmarchi.htm#BRADV89375" },
 { "t": "Oracle Secure Backup", "h": "rcmarchi.htm#BRADV89376" },
 { "t": "Backup Solutions Program", "h": "rcmarchi.htm#BRADV89377" },
 { }
 ]
 },
 { "t": "Fast Recovery Area", "h": "rcmarchi.htm#BRADV89378" },
{ "a": "e10642idm140591956643056", "t": "RMAN in a Data Guard Environment", "h": "rcmarchi.htm#BRADV89379", 
 "c": [ { "t": "RMAN Configuration in a Data Guard Environment", "h": "rcmarchi.htm#BRADV89380" },
 { "t": "RMAN File Management in a Data Guard Environment", "h": "rcmarchi.htm#BRADV89381" },
 { }
 ]
 },
 { }
 ]
 },
{ "a": "e10642idm140592020587536", "t": "Starting and Interacting with the RMAN\u00A0Client", "h": "rcmcnctg.htm#BRADV005", 
 "c": [ { "t": "Starting and Exiting RMAN", "h": "rcmcnctg.htm#BRADV8121" },
 { "t": "Specifying the Location of RMAN Output", "h": "rcmcnctg.htm#BRADV89382" },
 { "t": "Setting Globalization Support Environment Variables for RMAN", "h": "rcmcnctg.htm#BRADV8122" },
{ "a": "e10642idm140591984238464", "t": "Entering RMAN Commands", "h": "rcmcnctg.htm#BRADV89383", 
 "c": [ { "t": "Entering RMAN Commands at the RMAN Prompt", "h": "rcmcnctg.htm#BRADV89384" },
 { "t": "Using Command Files with RMAN", "h": "rcmcnctg.htm#BRADV89385" },
 { "t": "Entering Comments in RMAN Command Files", "h": "rcmcnctg.htm#BRADV99960" },
 { "t": "Using Substitution Variables in Command Files", "h": "rcmcnctg.htm#BRADV89386" },
 { "t": "Checking RMAN Syntax", "h": "rcmcnctg.htm#BRADV89387" },
 { }
 ]
 },
{ "a": "e10642idm140591973440848", "t": "Making Database Connections with RMAN", "h": "rcmcnctg.htm#BRADV8123", 
 "c": [ { "t": "About RMAN Database Connections", "h": "rcmcnctg.htm#BRADV89390" },
 { "t": "Making RMAN Database Connections from the Operating System Command Line", "h": "rcmcnctg.htm#BRADV89392" },
 { "t": "Making Database Connections from the RMAN Prompt", "h": "rcmcnctg.htm#BRADV89393" },
 { "t": "Connecting RMAN to an Auxiliary Database", "h": "rcmcnctg.htm#BRADV128" },
 { "t": "Making RMAN Database Connections Within Command Files", "h": "rcmcnctg.htm#BRADV129" },
 { "t": "Diagnosing RMAN Connection Problems", "h": "rcmcnctg.htm#BRADV89394" },
 { }
 ]
 },
{ "a": "e10642idm140592016115120", "t": "Using the RMAN Pipe Interface", "h": "rcmcnctg.htm#BRADV1130", 
 "c": [ { "t": "Executing Multiple RMAN Commands in Succession Through a Pipe: Example", "h": "rcmcnctg.htm#BRADV89397" },
 { "t": "Executing RMAN Commands in a Single Job Through a Pipe: Example", "h": "rcmcnctg.htm#BRADV89398" },
 { }
 ]
 },
 { }
 ]
 },
{ "a": "e10642idm140592005691552", "t": "Configuring the RMAN Environment", "h": "rcmconfb.htm#BRADV8002", 
 "c": [{ "a": "e10642idm140591991006896", "t": "Configuring the Environment for RMAN Backups", "h": "rcmconfb.htm#BRADV99961", 
 "c": [ { "t": "Showing and Clearing Persistent RMAN Configurations", "h": "rcmconfb.htm#BRADV8124" },
 { "t": "Configuring the Default Device for Backups: Disk or SBT", "h": "rcmconfb.htm#BRADV89399" },
 { "t": "Configuring the Default Type for Backups: Backup Sets or Copies", "h": "rcmconfb.htm#BRADV89400" },
 { "t": "Configuring Channels", "h": "rcmconfb.htm#BRADV89402" },
 { "t": "Configuring Control File and Server Parameter File Autobackups", "h": "rcmconfb.htm#BRADV89407" },
 { }
 ]
 },
{ "a": "e10642idm140591985688528", "t": "Configuring RMAN to Make Backups to a Media Manager", "h": "rcmconfb.htm#BRADV132", 
 "c": [ { "t": "Prerequisites for Using a Media Manager with RMAN", "h": "rcmconfb.htm#BRADV89409" },
 { "t": "Determining the Location of the Media Management Library", "h": "rcmconfb.htm#BRADV89410" },
 { "t": "Configuring Media Management Software for RMAN Backups", "h": "rcmconfb.htm#BRADV89411" },
 { "t": "Testing Whether the Media Manager Library Is Integrated Correctly", "h": "rcmconfb.htm#BRADV89412" },
 { "t": "Configuring SBT Channels for Use with a Media Manager", "h": "rcmconfb.htm#BRADV89415" },
 { }
 ]
 },
{ "a": "e10642idm140592085183424", "t": "Configuring the Fast Recovery Area", "h": "rcmconfb.htm#BRADV8183", 
 "c": [ { "t": "Overview of the Fast Recovery Area", "h": "rcmconfb.htm#BRADV89418" },
 { "t": "Enabling the Fast Recovery Area", "h": "rcmconfb.htm#BRADV89425" },
 { "t": "Disabling the Fast Recovery Area", "h": "rcmconfb.htm#BRADV528" },
 { "t": "Configuring Locations for Control Files and Redo Logs", "h": "rcmconfb.htm#BRADV89428" },
 { "t": "Configuring RMAN File Creation in the Fast Recovery Area", "h": "rcmconfb.htm#BRADV89432" },
 { }
 ]
 },
{ "a": "e10642idm140591984477088", "t": "Configuring the Backup Retention Policy", "h": "rcmconfb.htm#BRADV8400", 
 "c": [ { "t": "Configuring a Redundancy-Based Retention Policy", "h": "rcmconfb.htm#BRADV89436" },
 { "t": "Configuring a Recovery Window-Based Retention Policy", "h": "rcmconfb.htm#BRADV89437" },
 { "t": "Disabling the Retention Policy", "h": "rcmconfb.htm#BRADV89438" },
 { }
 ]
 },
{ "a": "e10642idm140591995843104", "t": "Backup Optimization and the CONFIGURE command", "h": "rcmconfb.htm#BRADV138", 
 "c": [ { "t": "Overview of Backup Optimization", "h": "rcmconfb.htm#BRADV113" },
 { "t": "Effect of Retention Policies on Backup Optimization for SBT Backups", "h": "rcmconfb.htm#BRADV89462" },
 { "t": "Configuring Backup Optimization", "h": "rcmconfb.htm#BRADV89465" },
 { }
 ]
 },
{ "a": "e10642idm140592000637648", "t": "Configuring an Archived Redo Log Deletion Policy", "h": "rcmconfb.htm#BRADV89439", 
 "c": [ { "t": "About Archived Redo Log Deletion Policies", "h": "rcmconfb.htm#BRADV89440" },
 { "t": "Enabling an Archived Redo Log Deletion Policy", "h": "rcmconfb.htm#BRADV89441" },
 { }
 ]
 },
 { "t": "Configuring RMAN in a Data Guard Environment", "h": "rcmconfb.htm#BRADV89455" },
 { }
 ]
 },
{ "a": "e10642idm140592020450416", "t": "Configuring the RMAN Environment: Advanced Topics", "h": "rcmconfa.htm#BRADV006", 
 "c": [{ "a": "e10642idm140592010999648", "t": "Configuring Advanced Channel Options", "h": "rcmconfa.htm#BRADV134", 
 "c": [ { "t": "About Channel Control Options", "h": "rcmconfa.htm#BRADV89456" },
 { "t": "Configuring Specific Channel Parameters", "h": "rcmconfa.htm#BRADV89457" },
 { }
 ]
 },
{ "a": "e10642idm140591982618704", "t": "Configuring Advanced Backup Options", "h": "rcmconfa.htm#BRADV89460", 
 "c": [ { "t": "Configuring the Maximum Size of Backup Sets", "h": "rcmconfa.htm#BRADV137" },
 { "t": "Configuring the Maximum Size of Backup Pieces", "h": "rcmconfa.htm#BRADV89461" },
 { "t": "Configuring Backup Duplexing", "h": "rcmconfa.htm#BRADV139" },
 { "t": "Configuring Tablespaces for Exclusion from Whole Database Backups", "h": "rcmconfa.htm#BRADV140" },
 { "t": "Configuring Compression Options", "h": "rcmconfa.htm#BRADV89466" },
 { "t": "Configuring Backup Encryption", "h": "rcmconfa.htm#BRADV89467" },
 { }
 ]
 },
 { "t": "Configuring Auxiliary Instance Data File Names", "h": "rcmconfa.htm#BRADV14011" },
{ "a": "e10642idm140592022615808", "t": "Configuring the Snapshot Control File Location", "h": "rcmconfa.htm#BRADV141", 
 "c": [ { "t": "Viewing the Configured Location of the Snapshot Control File", "h": "rcmconfa.htm#BRADV89474" },
 { "t": "Setting the Location of the Snapshot Control File", "h": "rcmconfa.htm#BRADV89475" },
 { }
 ]
 },
 { "t": "Configuring RMAN for Use with a Shared Server", "h": "rcmconfa.htm#BRADV142" },
 { "t": "Enabling Lost Write Detection", "h": "rcmconfa.htm#BRADV89476" },
 { }
 ]
 },
{ "a": "e10642idm140591959712720", "t": "Using Flashback Database and Restore Points", "h": "flashdb.htm#BRADV71000", 
 "c": [{ "a": "e10642idm140592070522192", "t": "Understanding Flashback Database, Restore Points and Guaranteed Restore Points", "h": "flashdb.htm#BRADV180", 
 "c": [ { "t": "Flashback Database", "h": "flashdb.htm#BRADV582" },
 { "t": "Flashback Database Window", "h": "flashdb.htm#BRADV583" },
 { "t": "Limitations of Flashback Database", "h": "flashdb.htm#BRADV286" },
 { "t": "Normal Restore Points", "h": "flashdb.htm#BRADV529" },
 { "t": "Guaranteed Restore Points", "h": "flashdb.htm#BRADV530" },
 { }
 ]
 },
{ "a": "e10642idm140591948116736", "t": "Logging for Flashback Database and Guaranteed Restore Points", "h": "flashdb.htm#BRADV577", 
 "c": [ { "t": "Guaranteed Restore Points and Fast Recovery Area Space Usage", "h": "flashdb.htm#BRADV581" },
 { "t": "Logging for Guaranteed Restore Points with Flashback Logging Disabled", "h": "flashdb.htm#BRADV584" },
 { "t": "Logging for Flashback Database with Guaranteed Restore Points Defined", "h": "flashdb.htm#BRADV585" },
 { }
 ]
 },
 { "t": "Prerequisites for Flashback Database and Guaranteed Restore Points", "h": "flashdb.htm#BRADV586" },
{ "a": "e10642idm140591990995984", "t": "Using Normal and Guaranteed Restore Points", "h": "flashdb.htm#BRADV589", 
 "c": [ { "t": "Creating Normal and Guaranteed Restore Points", "h": "flashdb.htm#BRADV590" },
 { "t": "Listing Restore Points", "h": "flashdb.htm#BRADV592" },
 { "t": "Dropping Restore Points", "h": "flashdb.htm#BRADV593" },
 { }
 ]
 },
{ "a": "e10642idm140592010474448", "t": "Using Flashback Database", "h": "flashdb.htm#BRADV594", 
 "c": [ { "t": "Enabling Flashback Database", "h": "flashdb.htm#BRADV595" },
 { "t": "Disabling Flashback Database Logging", "h": "flashdb.htm#BRADV597" },
 { "t": "Configuring the Environment for Optimal Flashback Database Performance", "h": "flashdb.htm#BRADV598" },
 { "t": "Monitoring the Effect of Flashback Database on Performance", "h": "flashdb.htm#BRADV599" },
 { "t": "Flashback Writer (RVWR) Behavior with I/O Errors", "h": "flashdb.htm#BRADV601" },
 { }
 ]
 },
 { }
 ]
 },
{ "a": "e10642idm140591984465600", "t": "RMAN Backup Concepts", "h": "rcmcncpt.htm#BRADV002", 
 "c": [{ "a": "e10642idm140591957865792", "t": "Consistent and Inconsistent RMAN Backups", "h": "rcmcncpt.htm#BRADV89477", 
 "c": [ { "t": "Consistent Backups", "h": "rcmcncpt.htm#BRADV99964" },
 { "t": "Inconsistent Backups", "h": "rcmcncpt.htm#BRADV99965" },
 { }
 ]
 },
 { "t": "Online Backups and Backup Mode", "h": "rcmcncpt.htm#BRADV89479" },
{ "a": "e10642idm140592012459680", "t": "Backup Sets", "h": "rcmcncpt.htm#BRADV106", 
 "c": [ { "t": "Backup Sets and Backup Pieces", "h": "rcmcncpt.htm#BRADV89480" },
 { "t": "Block Compression for Backup Sets", "h": "rcmcncpt.htm#BRADV89481" },
 { "t": "Binary Compression for Backup Sets", "h": "rcmcncpt.htm#BRADV194" },
 { "t": "Backup Undo", "h": "rcmcncpt.htm#BRADV195" },
 { "t": "Encryption for Backup Sets", "h": "rcmcncpt.htm#BRADV89482" },
 { "t": "Filenames for Backup Pieces", "h": "rcmcncpt.htm#BRADV89483" },
 { "t": "Number and Size of Backup Pieces", "h": "rcmcncpt.htm#BRADV89484" },
 { "t": "Number and Size of Backup Sets", "h": "rcmcncpt.htm#BRADV89485" },
 { "t": "Multiplexed Backup Sets", "h": "rcmcncpt.htm#BRADV89486" },
 { "t": "Proxy Copies", "h": "rcmcncpt.htm#BRADV89487" },
 { }
 ]
 },
{ "a": "e10642idm140592090616656", "t": "Image Copies", "h": "rcmcncpt.htm#BRADV89488", 
 "c": [ { "t": "RMAN-Created Image Copies", "h": "rcmcncpt.htm#BRADV89489" },
 { "t": "User-Managed Image Copies", "h": "rcmcncpt.htm#BRADV89490" },
 { }
 ]
 },
{ "a": "e10642idm140592088134480", "t": "Multiple Copies of RMAN Backups", "h": "rcmcncpt.htm#BRADV107", 
 "c": [ { "t": "Duplexed Backup Sets", "h": "rcmcncpt.htm#BRADV89491" },
 { "t": "Backups of Backups", "h": "rcmcncpt.htm#BRADV89492" },
 { }
 ]
 },
{ "a": "e10642idm140591974037248", "t": "Control File and Server Parameter File Autobackups", "h": "rcmcncpt.htm#BRADV111", 
 "c": [ { "t": "When RMAN Performs Control File Autobackups", "h": "rcmcncpt.htm#BRADV89495" },
 { "t": "How RMAN Performs Control File Autobackups", "h": "rcmcncpt.htm#BRADV89496" },
 { }
 ]
 },
{ "a": "e10642idm140592005364576", "t": "Incremental Backups", "h": "rcmcncpt.htm#BRADV109", 
 "c": [ { "t": "Multilevel Incremental Backups", "h": "rcmcncpt.htm#BRADV89499" },
 { "t": "Block Change Tracking", "h": "rcmcncpt.htm#BRADV90078" },
 { "t": "Incremental Backup Algorithm", "h": "rcmcncpt.htm#BRADV89498" },
 { "t": "Recovery with Incremental Backups", "h": "rcmcncpt.htm#BRADV89497" },
 { }
 ]
 },
{ "a": "e10642idm140591988714720", "t": "Backup Retention Policies", "h": "rcmcncpt.htm#BRADV99966", 
 "c": [ { "t": "Recovery Window", "h": "rcmcncpt.htm#BRADV89502" },
 { "t": "Backup Redundancy", "h": "rcmcncpt.htm#BRADV89503" },
 { "t": "Batch Deletes of Obsolete Backups", "h": "rcmcncpt.htm#BRADV89504" },
 { "t": "Backup Retention Policy and Fast Recovery Area Deletion Rules", "h": "rcmcncpt.htm#BRADV89505" },
 { }
 ]
 },
 { }
 ]
 },
{ "a": "e10642idm140592012173376", "t": "Backing Up the Database", "h": "rcmbckba.htm#BRADV8003", 
 "c": [{ "a": "e10642idm140592019972592", "t": "Overview of RMAN Backups", "h": "rcmbckba.htm#BRADV8131", 
 "c": [ { "t": "Purpose of RMAN Backups", "h": "rcmbckba.htm#BRADV89506" },
 { "t": "Basic Concepts of RMAN Backups", "h": "rcmbckba.htm#BRADV89507" },
 { }
 ]
 },
{ "a": "e10642idm140591994548752", "t": "Specifying Backup Output Options", "h": "rcmbckba.htm#BRADV89508", 
 "c": [ { "t": "Specifying the Device Type for an RMAN Backup", "h": "rcmbckba.htm#BRADV89509" },
 { "t": "Specifying Backup Set or Copy for an RMAN Backup to Disk", "h": "rcmbckba.htm#BRADV89510" },
 { "t": "Specifying a Format for RMAN Backups", "h": "rcmbckba.htm#BRADV89511" },
 { "t": "Specifying Tags for an RMAN Backup", "h": "rcmbckba.htm#BRADV89513" },
 { "t": "Making Compressed Backups", "h": "rcmbckba.htm#BRADV8138" },
 { }
 ]
 },
{ "a": "e10642idm140592005561312", "t": "Backing Up Database Files with RMAN", "h": "rcmbckba.htm#BRADV8132", 
 "c": [ { "t": "Backing Up a Whole Database with RMAN", "h": "rcmbckba.htm#BRADV8231" },
 { "t": "Backing Up Tablespaces and Datafiles with RMAN", "h": "rcmbckba.htm#BRADV89516" },
 { "t": "Backing Up Control Files with RMAN", "h": "rcmbckba.htm#BRADV89517" },
 { "t": "Backing Up Server Parameter Files with RMAN", "h": "rcmbckba.htm#BRADV89519" },
 { "t": "Backing Up a Database in NOARCHIVELOG Mode", "h": "rcmbckba.htm#BRADV89526" },
 { }
 ]
 },
{ "a": "e10642idm140592021252272", "t": "Backing Up Archived Redo Logs with RMAN", "h": "rcmbckba.htm#BRADV81399", 
 "c": [ { "t": "About Backups of Archived Redo Logs", "h": "rcmbckba.htm#BRADV89520" },
 { "t": "Backing Up Archived Redo Log Files", "h": "rcmbckba.htm#BRADV89525" },
 { "t": "Backing Up Only Archived Redo Logs That Need Backups", "h": "rcmbckba.htm#BRADV89522" },
 { "t": "Deleting Archived Redo Logs After Backups", "h": "rcmbckba.htm#BRADV89524" },
 { }
 ]
 },
{ "a": "e10642idm140591941913120", "t": "Making and Updating Incremental Backups", "h": "rcmbckba.htm#BRADV8133", 
 "c": [ { "t": "Purpose of Incremental Backups", "h": "rcmbckba.htm#BRADV89527" },
 { "t": "Planning an Incremental Backup Strategy", "h": "rcmbckba.htm#BRADV89528" },
 { "t": "Making Incremental Backups", "h": "rcmbckba.htm#BRADV89529" },
 { "t": "Incrementally Updating Backups", "h": "rcmbckba.htm#BRADV8186" },
 { "t": "Using Block Change Tracking to Improve Incremental Backup Performance", "h": "rcmbckba.htm#BRADV8125" },
 { }
 ]
 },
{ "a": "e10642idm140591957419584", "t": "Making Database Backups for Long-Term Storage", "h": "rcmbckba.htm#BRADV89551", 
 "c": [ { "t": "Purpose of Archival Backups", "h": "rcmbckba.htm#BRADV89552" },
 { "t": "Basic Concepts of Archival Backups", "h": "rcmbckba.htm#BRADV89553" },
 { "t": "Making an Archival Backup for Long-Term Storage", "h": "rcmbckba.htm#BRADV89554" },
 { "t": "Making a Temporary Archival Backup", "h": "rcmbckba.htm#BRADV89556" },
 { }
 ]
 },
{ "a": "e10642idm140592004397152", "t": "Backing Up RMAN Backups", "h": "rcmbckba.htm#BRADV89557", 
 "c": [ { "t": "About Backups of Backups", "h": "rcmbckba.htm#BRADV89558" },
 { "t": "Backing Up Backup Sets with RMAN", "h": "rcmbckba.htm#BRADV147" },
 { "t": "Backing Up Image Copy Backups with RMAN", "h": "rcmbckba.htm#BRADV89561" },
 { }
 ]
 },
 { }
 ]
 },
{ "a": "e10642idm140592020964832", "t": "Backing Up the Database: Advanced Topics", "h": "rcmbckad.htm#BRADV007", 
 "c": [{ "a": "e10642idm140592023045760", "t": "Limiting the Size of RMAN Backup Sets", "h": "rcmbckad.htm#BRADV89540", 
 "c": [ { "t": "About Backup Set Size", "h": "rcmbckad.htm#BRADV89541" },
 { "t": "Limiting the Size of Backup Sets with BACKUP ... MAXSETSIZE", "h": "rcmbckad.htm#BRADV89542" },
 { "t": "Dividing the Backup of a Large Data File into Sections", "h": "rcmbckad.htm#BRADV89543" },
 { }
 ]
 },
{ "a": "e10642idm140591982299584", "t": "Using Backup Optimization to Skip Files", "h": "rcmbckad.htm#BRADV89546", 
 "c": [ { "t": "Optimizing a Daily Archived Log Backup to a Single Tape: Scenario", "h": "rcmbckad.htm#BRADV89548" },
 { "t": "Optimizing a Daily Archived Log Backup to Multiple Media Families: Scenario", "h": "rcmbckad.htm#BRADV89549" },
 { "t": "Creating a Weekly Secondary Backup of Archived Logs: Example", "h": "rcmbckad.htm#BRADV89550" },
 { }
 ]
 },
 { "t": "Skipping Offline, Read-Only, and Inaccessible Files", "h": "rcmbckad.htm#BRADV89569" },
{ "a": "e10642idm140592014954992", "t": "Duplexing Backup Sets", "h": "rcmbckad.htm#BRADV145", 
 "c": [ { "t": "Duplexing Backup Sets with CONFIGURE BACKUP COPIES", "h": "rcmbckad.htm#BRADV89570" },
 { "t": "Duplexing Backup Sets with BACKUP ... COPIES", "h": "rcmbckad.htm#BRADV89571" },
 { }
 ]
 },
 { "t": "Making Split Mirror Backups with RMAN", "h": "rcmbckad.htm#BRADV146" },
{ "a": "e10642idm140591990071040", "t": "Encrypting RMAN Backups", "h": "rcmbckad.htm#BRADV72450", 
 "c": [ { "t": "About RMAN Backup Encryption Settings", "h": "rcmbckad.htm#BRADV89573" },
 { "t": "Making Transparent-Mode Encrypted Backups", "h": "rcmbckad.htm#BRADV89574" },
 { "t": "Making Password-Mode Encrypted Backups", "h": "rcmbckad.htm#BRADV89575" },
 { "t": "Making Dual-Mode Encrypted Backups", "h": "rcmbckad.htm#BRADV89576" },
 { }
 ]
 },
{ "a": "e10642idm140592021676048", "t": "Restarting RMAN Backups", "h": "rcmbckad.htm#BRADV148", 
 "c": [ { "t": "About Restartable Backups", "h": "rcmbckad.htm#BRADV114" },
 { "t": "Restarting a Backup After It Partially Completes", "h": "rcmbckad.htm#BRADV89577" },
 { }
 ]
 },
{ "a": "e10642idm140591958066656", "t": "Managing Backup Windows", "h": "rcmbckad.htm#BRADV301", 
 "c": [ { "t": "About Backup Windows", "h": "rcmbckad.htm#BRADV89578" },
 { "t": "Specifying a Backup Duration", "h": "rcmbckad.htm#BRADV89579" },
 { "t": "Permitting Partial Backups in a Backup Window", "h": "rcmbckad.htm#BRADV89580" },
 { "t": "Minimizing Backup Load and Duration", "h": "rcmbckad.htm#BRADV89581" },
 { }
 ]
 },
 { }
 ]
 },
{ "a": "e10642idm140591982031712", "t": "Reporting on RMAN Operations", "h": "rcmreprt.htm#BRADV8004", 
 "c": [{ "a": "e10642idm140591974123616", "t": "Overview of RMAN Reporting", "h": "rcmreprt.htm#BRADV8135", 
 "c": [ { "t": "Purpose of RMAN Reporting", "h": "rcmreprt.htm#BRADV89582" },
 { "t": "Basic Concepts of RMAN Reporting", "h": "rcmreprt.htm#BRADV89583" },
 { }
 ]
 },
{ "a": "e10642idm140591946692688", "t": "Listing Backups and Recovery-Related Objects", "h": "rcmreprt.htm#BRADV8136", 
 "c": [ { "t": "About the LIST Command", "h": "rcmreprt.htm#BRADV89585" },
 { "t": "Listing All Backups and Copies", "h": "rcmreprt.htm#BRADV89586" },
 { "t": "Listing Selected Backups and Copies", "h": "rcmreprt.htm#BRADV89589" },
 { "t": "Listing Database Incarnations", "h": "rcmreprt.htm#BRADV89591" },
 { }
 ]
 },
{ "a": "e10642idm140592008858544", "t": "Reporting on Backups and Database Schema", "h": "rcmreprt.htm#BRADV8137", 
 "c": [ { "t": "About Reports of RMAN Backups", "h": "rcmreprt.htm#BRADV89593" },
 { "t": "Reporting on Files Needing a Backup Under a Retention Policy", "h": "rcmreprt.htm#BRADV89594" },
 { "t": "Reporting on Datafiles Affected by Unrecoverable Operations", "h": "rcmreprt.htm#BRADV89598" },
 { "t": "Reporting on Obsolete Backups", "h": "rcmreprt.htm#BRADV89599" },
 { "t": "Reporting on the Database Schema", "h": "rcmreprt.htm#BRADV89600" },
 { }
 ]
 },
{ "a": "e10642idm140591975819888", "t": "Using V$ Views to Query Backup Metadata", "h": "rcmreprt.htm#BRADV90911", 
 "c": [ { "t": "Querying Details of Past and Current RMAN Jobs", "h": "rcmreprt.htm#BRADV99967" },
 { "t": "Determining the Encryption Status of Backup Pieces", "h": "rcmreprt.htm#BRADV90912" },
 { }
 ]
 },
{ "a": "e10642idm140592071990704", "t": "Querying Recovery Catalog Views", "h": "rcmreprt.htm#BRADV89601", 
 "c": [ { "t": "About Recovery Catalog Views", "h": "rcmreprt.htm#BRADV89602" },
 { "t": "Querying Catalog Views for the Target DB_KEY or DBID Values", "h": "rcmreprt.htm#BRADV89605" },
 { "t": "Querying RC_BACKUP_FILES", "h": "rcmreprt.htm#BRADV53532" },
 { }
 ]
 },
 { }
 ]
 },
{ "a": "e10642idm140591989035264", "t": "Maintaining RMAN Backups and Repository\u00A0Records", "h": "rcmmaint.htm#BRADV8007", 
 "c": [{ "a": "e10642idm140592006489456", "t": "Overview of RMAN Backup and Repository Maintenance", "h": "rcmmaint.htm#BRADV89607", 
 "c": [ { "t": "Purpose of Backup and Repository Maintenance", "h": "rcmmaint.htm#BRADV89608" },
 { "t": "Basic Concepts of Backup and Repository Maintenance", "h": "rcmmaint.htm#BRADV990" },
 { }
 ]
 },
{ "a": "e10642idm140592000284240", "t": "Maintaining the Control File Repository", "h": "rcmmaint.htm#BRADV8602", 
 "c": [ { "t": "About Control File Records", "h": "rcmmaint.htm#BRADV89609" },
 { "t": "Preventing the Loss of Control File Records", "h": "rcmmaint.htm#BRADV8206" },
 { "t": "Protecting the Control File", "h": "rcmmaint.htm#BRADV89611" },
 { }
 ]
 },
{ "a": "e10642idm140591978993600", "t": "Maintaining the Fast Recovery Area", "h": "rcmmaint.htm#BRADV89612", 
 "c": [ { "t": "Deletion Rules for the Fast Recovery Area", "h": "rcmmaint.htm#BRADV89613" },
 { "t": "Monitoring Fast Recovery Area Space Usage", "h": "rcmmaint.htm#BRADV89614" },
 { "t": "Managing Space for Flashback Logs in the Fast Recovery Area", "h": "rcmmaint.htm#BRADV89615" },
 { "t": "Responding to a Full Fast Recovery Area", "h": "rcmmaint.htm#BRADV89616" },
 { "t": "Changing the Fast Recovery Area to a New Location", "h": "rcmmaint.htm#BRADV89618" },
 { "t": "Disabling the Fast Recovery Area", "h": "rcmmaint.htm#BRADV89619" },
 { "t": "Responding to an Instance Crash During File Creation", "h": "rcmmaint.htm#BRADV89620" },
 { }
 ]
 },
{ "a": "e10642idm140592092947616", "t": "Updating the RMAN Repository", "h": "rcmmaint.htm#BRADV89623", 
 "c": [ { "t": "Crosschecking the RMAN Repository", "h": "rcmmaint.htm#BRADV8171" },
 { "t": "Changing the Repository Status of Backups and Copies", "h": "rcmmaint.htm#BRADV8173" },
 { "t": "Adding Backup Records to the RMAN Repository", "h": "rcmmaint.htm#BRADV8174" },
 { "t": "Removing Records from the RMAN Repository", "h": "rcmmaint.htm#BRADV8175" },
 { }
 ]
 },
{ "a": "e10642idm140591999214304", "t": "Deleting RMAN Backups and Archived Redo Logs", "h": "rcmmaint.htm#BRADV8172", 
 "c": [ { "t": "Overview of RMAN Deletion", "h": "rcmmaint.htm#BRADV89632" },
 { "t": "Deleting All Backups and Copies", "h": "rcmmaint.htm#BRADV89633" },
 { "t": "Deleting Specified Backups and Copies", "h": "rcmmaint.htm#BRADV89634" },
 { "t": "Deleting Expired RMAN Backups and Copies", "h": "rcmmaint.htm#BRADV89637" },
 { "t": "Deleting Obsolete RMAN Backups Based on Retention Policies", "h": "rcmmaint.htm#BRADV89639" },
 { }
 ]
 },
 { "t": "Dropping a Database", "h": "rcmmaint.htm#BRADV89641" },
 { }
 ]
 },
{ "a": "e10642idm140592084961744", "t": "Managing a Recovery Catalog", "h": "rcmcatdb.htm#BRADV8015", 
 "c": [{ "a": "e10642idm140592002483504", "t": "Overview of the Recovery Catalog", "h": "rcmcatdb.htm#BRADV89642", 
 "c": [ { "t": "Purpose of the Recovery Catalog", "h": "rcmcatdb.htm#BRADV89643" },
 { "t": "Basic Concepts for the Recovery Catalog", "h": "rcmcatdb.htm#BRADV89644" },
 { "t": "Basic Steps of Managing a Recovery Catalog", "h": "rcmcatdb.htm#BRADV89646" },
 { }
 ]
 },
{ "a": "e10642idm140592002854992", "t": "Creating a Recovery Catalog", "h": "rcmcatdb.htm#BRADV179", 
 "c": [ { "t": "Configuring the Recovery Catalog Database", "h": "rcmcatdb.htm#BRADV89647" },
 { "t": "Creating the Recovery Catalog Schema Owner", "h": "rcmcatdb.htm#BRADV89650" },
 { "t": "Executing the CREATE CATALOG Command", "h": "rcmcatdb.htm#BRADV89651" },
 { }
 ]
 },
{ "a": "e10642idm140591981234416", "t": "Registering a Database in the Recovery Catalog", "h": "rcmcatdb.htm#BRADV11001", 
 "c": [ { "t": "About Registration of a Database in the Recovery Catalog", "h": "rcmcatdb.htm#BRADV89652" },
 { "t": "Registering a Database with the REGISTER DATABASE Command", "h": "rcmcatdb.htm#BRADV89654" },
 { }
 ]
 },
 { "t": "Cataloging Backups in the Recovery Catalog", "h": "rcmcatdb.htm#BRADV89655" },
{ "a": "e10642idm140592006446960", "t": "Creating and Managing Virtual Private Catalogs", "h": "rcmcatdb.htm#BRADV89656", 
 "c": [ { "t": "About Virtual Private Catalogs", "h": "rcmcatdb.htm#BRADV89657" },
 { "t": "Creating and Granting Privileges to a Virtual Private Catalog Owner", "h": "rcmcatdb.htm#BRADV89658" },
 { "t": "Creating a Virtual Private Catalog", "h": "rcmcatdb.htm#BRADV89659" },
 { "t": "Revoking Privileges from a Virtual Private Catalog Owner", "h": "rcmcatdb.htm#BRADV89660" },
 { "t": "Dropping a Virtual Private Catalog", "h": "rcmcatdb.htm#BRADV89661" },
 { }
 ]
 },
{ "a": "e10642idm140591947603664", "t": "Protecting the Recovery Catalog", "h": "rcmcatdb.htm#BRADV89662", 
 "c": [ { "t": "Backing Up the Recovery Catalog", "h": "rcmcatdb.htm#BRADV89663" },
 { "t": "Recovering the Recovery Catalog", "h": "rcmcatdb.htm#BRADV89668" },
 { }
 ]
 },
{ "a": "e10642idm140592087949168", "t": "Managing Stored Scripts", "h": "rcmcatdb.htm#BRADV182", 
 "c": [ { "t": "About Stored Scripts", "h": "rcmcatdb.htm#BRADV89669" },
 { "t": "Creating Stored Scripts", "h": "rcmcatdb.htm#BRADV89670" },
 { "t": "Replacing Stored Scripts", "h": "rcmcatdb.htm#BRADV89671" },
 { "t": "Executing Stored Scripts", "h": "rcmcatdb.htm#BRADV89672" },
 { "t": "Creating and Executing Dynamic Stored Scripts", "h": "rcmcatdb.htm#BRADV89673" },
 { "t": "Printing Stored Scripts", "h": "rcmcatdb.htm#BRADV89674" },
 { "t": "Listing Stored Script Names", "h": "rcmcatdb.htm#BRADV89675" },
 { "t": "Deleting Stored Scripts", "h": "rcmcatdb.htm#BRADV89676" },
 { "t": "Executing a Stored Script at RMAN Startup", "h": "rcmcatdb.htm#BRADV89677" },
 { }
 ]
 },
{ "a": "e10642idm140592048680512", "t": "Maintaining a Recovery Catalog", "h": "rcmcatdb.htm#BRADV89678", 
 "c": [ { "t": "About Recovery Catalog Maintenance", "h": "rcmcatdb.htm#BRADV89679" },
 { "t": "Resynchronizing the Recovery Catalog", "h": "rcmcatdb.htm#BRADV181" },
 { "t": "Updating the Recovery Catalog After Changing a DB_UNIQUE_NAME", "h": "rcmcatdb.htm#BRADV89690" },
 { "t": "Unregistering a Target Database from the Recovery Catalog", "h": "rcmcatdb.htm#BRADV89691" },
 { "t": "Resetting the Database Incarnation in the Recovery Catalog", "h": "rcmcatdb.htm#BRADV89694" },
 { "t": "Upgrading the Recovery Catalog", "h": "rcmcatdb.htm#BRADV188" },
 { "t": "Importing and Moving a Recovery Catalog", "h": "rcmcatdb.htm#BRADV89698" },
 { }
 ]
 },
 { "t": "Dropping a Recovery Catalog", "h": "rcmcatdb.htm#BRADV189" },
 { }
 ]
 },
{ "a": "e10642idm140591981082192", "t": "RMAN Data Repair Concepts", "h": "rcmrvcon.htm#BRADV89703", 
 "c": [{ "a": "e10642idm140592093429280", "t": "Overview of RMAN Data Repair", "h": "rcmrvcon.htm#BRADV8199", 
 "c": [ { "t": "Problems Requiring Data Repair", "h": "rcmrvcon.htm#BRADV89704" },
 { "t": "RMAN Data Repair Techniques", "h": "rcmrvcon.htm#BRADV89708" },
 { }
 ]
 },
{ "a": "e10642idm140592087797680", "t": "RMAN Restore Operations", "h": "rcmrvcon.htm#BRADV116", 
 "c": [ { "t": "Backup Selection", "h": "rcmrvcon.htm#BRADV89709" },
 { "t": "Restore Failover", "h": "rcmrvcon.htm#BRADV30001" },
 { "t": "About RMAN Restore Operations and ASM", "h": "rcmrvcon.htm" },
 { "t": "Restore Optimization", "h": "rcmrvcon.htm#BRADV89710" },
 { }
 ]
 },
{ "a": "e10642idm140591977039488", "t": "RMAN Media Recovery", "h": "rcmrvcon.htm#BRADV117", 
 "c": [ { "t": "Selection of Incremental Backups and Archived Redo Logs", "h": "rcmrvcon.htm#BRADV89711" },
 { "t": "Database Incarnations", "h": "rcmrvcon.htm#BRADV1171" },
 { }
 ]
 },
 { }
 ]
 },
{ "a": "e10642idm140592096308080", "t": "Diagnosing and Repairing Failures with Data Recovery Advisor", "h": "rcmrepai.htm#BRADV246", 
 "c": [{ "a": "e10642idm140592006403488", "t": "Overview of Data Recovery Advisor", "h": "rcmrepai.htm#BRADV89714", 
 "c": [ { "t": "Purpose of Data Recovery Advisor", "h": "rcmrepai.htm#BRADV89715" },
 { "t": "Basic Concepts of Data Recovery Advisor", "h": "rcmrepai.htm#BRADV89716" },
 { "t": "Basic Steps of Diagnosing and Repairing Failures", "h": "rcmrepai.htm#BRADV89725" },
 { }
 ]
 },
{ "a": "e10642idm140592093316464", "t": "Listing Failures", "h": "rcmrepai.htm#BRADV89726", 
 "c": [ { "t": "Listing All Failures", "h": "rcmrepai.htm#BRADV89727" },
 { "t": "Listing a Subset of Failures", "h": "rcmrepai.htm#BRADV89728" },
 { }
 ]
 },
 { "t": "Checking for Block Corruptions by Validating the Database", "h": "rcmrepai.htm#BRADV89729" },
{ "a": "e10642idm140591947489904", "t": "Determining Repair Options", "h": "rcmrepai.htm#BRADV89730", 
 "c": [ { "t": "Determining Repair Options for All Failures", "h": "rcmrepai.htm#BRADV89731" },
 { "t": "Determining Repair Options for a Subset of Failures", "h": "rcmrepai.htm#BRADV89732" },
 { }
 ]
 },
{ "a": "e10642idm140591976392704", "t": "Repairing Failures", "h": "rcmrepai.htm#BRADV89733", 
 "c": [ { "t": "About Repairing Failures", "h": "rcmrepai.htm#BRADV89734" },
 { "t": "Repairing a Failure", "h": "rcmrepai.htm#BRADV89735" },
 { }
 ]
 },
 { "t": "Changing Failure Status and Priority", "h": "rcmrepai.htm#BRADV89736" },
 { }
 ]
 },
{ "a": "e10642idm140592039652512", "t": "Validating Database Files and Backups", "h": "rcmvalid.htm#BRADV90063", 
 "c": [{ "a": "e10642idm140592099345072", "t": "Overview of RMAN Validation", "h": "rcmvalid.htm#BRADV115", 
 "c": [ { "t": "Purpose of RMAN Validation", "h": "rcmvalid.htm#BRADV90064" },
 { "t": "Basic Concepts of RMAN Validation", "h": "rcmvalid.htm#BRADV90065" },
 { }
 ]
 },
 { "t": "Checking for Block Corruption with the VALIDATE Command", "h": "rcmvalid.htm#BRADV89563" },
 { "t": "Validating Database Files with BACKUP VALIDATE", "h": "rcmvalid.htm#BRADV89562" },
 { "t": "Validating Backups Before Restoring Them", "h": "rcmvalid.htm#BRADV8156" },
 { }
 ]
 },
{ "a": "e10642idm140591979957216", "t": "Performing Complete Database Recovery", "h": "rcmcomre.htm#BRADV8005", 
 "c": [{ "a": "e10642idm140591981152048", "t": "Overview of Complete Database Recovery", "h": "rcmcomre.htm#BRADV89759", 
 "c": [ { "t": "Purpose of Complete Database Recovery", "h": "rcmcomre.htm#BRADV89760" },
 { "t": "Scope of This Chapter", "h": "rcmcomre.htm#BRADV89761" },
 { }
 ]
 },
{ "a": "e10642idm140592071365904", "t": "Preparing for Complete Database Recovery", "h": "rcmcomre.htm#BRADV89762", 
 "c": [ { "t": "Identifying the Database Files to Restore or Recover", "h": "rcmcomre.htm#BRADV89763" },
 { "t": "Determining the DBID of the Database", "h": "rcmcomre.htm#BRADV80002" },
 { "t": "Previewing Backups Used in Restore Operations", "h": "rcmcomre.htm#BRADV8140" },
 { "t": "Validating Backups Before Restoring Them", "h": "rcmcomre.htm#BRADV90066" },
 { "t": "Restoring Archived Redo Logs Needed for Recovery", "h": "rcmcomre.htm#BRADV89778" },
 { }
 ]
 },
{ "a": "e10642idm140592021616912", "t": "Performing Complete Database Recovery", "h": "rcmcomre.htm#BRADV8152", 
 "c": [ { "t": "About Complete Database Recovery", "h": "rcmcomre.htm#BRADV89771" },
 { "t": "Performing Complete Recovery of the Whole Database", "h": "rcmcomre.htm#BRADV89772" },
 { "t": "Performing Complete Recovery of a Tablespace", "h": "rcmcomre.htm#BRADV89773" },
 { "t": "Performing Complete Recovery After Switching to a Copy", "h": "rcmcomre.htm#BRADV89774" },
 { }
 ]
 },
 { }
 ]
 },
{ "a": "e10642idm140592002871552", "t": "Performing Flashback and Database Point-in-Time Recovery", "h": "rcmflash.htm#BRADV80055", 
 "c": [{ "a": "e10642idm140592019435584", "t": "Overview of Oracle Flashback Technology and Database Point-in-Time Recovery", "h": "rcmflash.htm#BRADV89737", 
 "c": [ { "t": "Purpose of Flashback and Database Point-in-Time-Recovery", "h": "rcmflash.htm#BRADV89738" },
 { "t": "Basic Concepts of Point-in-Time Recovery and Flashback Features", "h": "rcmflash.htm#BRADV89739" },
 { }
 ]
 },
{ "a": "e10642idm140591947147120", "t": "Rewinding a Table with Flashback Table", "h": "rcmflash.htm#BRADV81517", 
 "c": [ { "t": "Prerequisites of Flashback Table", "h": "rcmflash.htm#BRADV89743" },
 { "t": "Performing a Flashback Table Operation", "h": "rcmflash.htm#BRADV89744" },
 { }
 ]
 },
{ "a": "e10642idm140592086948816", "t": "Rewinding a DROP TABLE Operation with Flashback Drop", "h": "rcmflash.htm#BRADV81511", 
 "c": [ { "t": "About Flashback Drop", "h": "rcmflash.htm#BRADV89746" },
 { "t": "Prerequisites of Flashback Drop", "h": "rcmflash.htm#BRADV89747" },
 { "t": "Performing a Flashback Drop Operation", "h": "rcmflash.htm#BRADV89748" },
 { }
 ]
 },
{ "a": "e10642idm140592012568544", "t": "Rewinding a Database with Flashback Database", "h": "rcmflash.htm#BRADV81330", 
 "c": [ { "t": "Prerequisites of Flashback Database", "h": "rcmflash.htm#BRADV89751" },
 { "t": "Performing a Flashback Database Operation", "h": "rcmflash.htm#BRADV89752" },
 { "t": "Monitoring Flashback Database", "h": "rcmflash.htm#BRADV603" },
 { }
 ]
 },
{ "a": "e10642idm140592070799536", "t": "Performing Database Point-in-Time Recovery", "h": "rcmflash.htm#BRADV84152", 
 "c": [ { "t": "Prerequisites of Database Point-in-Time Recovery", "h": "rcmflash.htm#BRADV89753" },
 { "t": "Performing Database Point-in-Time Recovery", "h": "rcmflash.htm#BRADV89754" },
 { }
 ]
 },
{ "a": "e10642idm140591996583296", "t": "Flashback and Database Point-in-Time Recovery Scenarios", "h": "rcmflash.htm#BRADV89755", 
 "c": [ { "t": "Rewinding an OPEN RESETLOGS Operation with Flashback Database", "h": "rcmflash.htm#BRADV85442" },
 { "t": "Rewinding the Database to an SCN in an Abandoned Incarnation Branch", "h": "rcmflash.htm#BRADV89758" },
 { "t": "Recovering the Database to an Ancestor Incarnation", "h": "rcmflash.htm#BRADV84153" },
 { }
 ]
 },
 { }
 ]
 },
{ "a": "e10642idm140592009918688", "t": "Performing Block Media Recovery", "h": "rcmblock.htm#BRADV89781", 
 "c": [{ "a": "e10642idm140592093386928", "t": "Overview of Block Media Recovery", "h": "rcmblock.htm#BRADV157", 
 "c": [ { "t": "Purpose of Block Media Recovery", "h": "rcmblock.htm#BRADV89782" },
 { "t": "Basic Concepts of Block Media Recovery", "h": "rcmblock.htm#BRADV118" },
 { }
 ]
 },
 { "t": "Prerequisites for Block Media Recovery", "h": "rcmblock.htm#BRADV89785" },
 { "t": "Recovering Individual Blocks", "h": "rcmblock.htm#BRADV89786" },
 { "t": "Recovering All Blocks in V$DATABASE_BLOCK_CORRUPTION", "h": "rcmblock.htm#BRADV200" },
 { }
 ]
 },
{ "a": "e10642idm140591977223312", "t": "Performing RMAN Recovery: Advanced Scenarios", "h": "rcmadvre.htm#BRADV008", 
 "c": [ { "t": "Recovering a NOARCHIVELOG Database with Incremental Backups", "h": "rcmadvre.htm#BRADV89841" },
{ "a": "e10642idm140592048725712", "t": "Restoring the Server Parameter File", "h": "rcmadvre.htm#BRADV85339", 
 "c": [ { "t": "Restoring the Server Parameter File from a Control File Autobackup", "h": "rcmadvre.htm#BRADV89829" },
 { "t": "Creating an Initialization Parameter File with RMAN", "h": "rcmadvre.htm#BRADV89830" },
 { }
 ]
 },
{ "a": "e10642idm140591979707296", "t": "Performing Recovery with a Backup Control File", "h": "rcmadvre.htm#BRADV154", 
 "c": [ { "t": "About Recovery with a Backup Control File", "h": "rcmadvre.htm#BRADV89834" },
 { "t": "Performing Recovery with a Backup Control File and No Recovery Catalog", "h": "rcmadvre.htm#BRADV89838" },
 { }
 ]
 },
{ "a": "e10642idm140591990616960", "t": "Performing Disaster Recovery", "h": "rcmadvre.htm#BRADV156", 
 "c": [ { "t": "Prerequisites of Disaster Recovery", "h": "rcmadvre.htm#BRADV89839" },
 { "t": "Recovering the Database After a Disaster", "h": "rcmadvre.htm#BRADV89840" },
 { }
 ]
 },
{ "a": "e10642idm140592007542128", "t": "Restoring a Database on a New Host", "h": "rcmadvre.htm#BRADV908", 
 "c": [ { "t": "Preparing to Restore a Database on a New Host", "h": "rcmadvre.htm#BRADV89831" },
 { "t": "Testing the Restore of a Database on a New Host", "h": "rcmadvre.htm#BRADV89833" },
 { }
 ]
 },
 { }
 ]
 },
{ "a": "e10642idm140591958799600", "t": "Performing RMAN Tablespace Point-in-Time Recovery (TSPITR)", "h": "rcmtspit.htm#BRADV009", 
 "c": [{ "a": "e10642idm140592001575280", "t": "Overview of RMAN TSPITR", "h": "rcmtspit.htm#BRADV89787", 
 "c": [ { "t": "Purpose of RMAN TSPITR", "h": "rcmtspit.htm#BRADV89788" },
 { "t": "Basic Concepts of RMAN TSPITR", "h": "rcmtspit.htm#BRADV160" },
 { }
 ]
 },
{ "a": "e10642idm140592006337520", "t": "TSPITR Restrictions, Special Cases, and Limitations", "h": "rcmtspit.htm#BRADV89790", 
 "c": [ { "t": "Limitations of TSPITR", "h": "rcmtspit.htm#BRADV89791" },
 { "t": "Special Considerations When Not Using a Recovery Catalog", "h": "rcmtspit.htm#BRADV89792" },
 { }
 ]
 },
{ "a": "e10642idm140592092790720", "t": "Planning and Preparing for TSPITR", "h": "rcmtspit.htm#BRADV161", 
 "c": [ { "t": "Step 1: Select the Right Target Time for TSPITR", "h": "rcmtspit.htm#BRADV910" },
 { "t": "Step 2: Determine the Recovery Set", "h": "rcmtspit.htm#BRADV89793" },
 { "t": "Step 3: Identify and Preserve Objects That Are Lost After TSPITR", "h": "rcmtspit.htm#BRADV89795" },
 { }
 ]
 },
 { "t": "Performing Fully Automated RMAN TSPITR", "h": "rcmtspit.htm#BRADV89796" },
{ "a": "e10642idm140592006022832", "t": "Overriding Defaults for RMAN TSPITR with an RMAN-Managed Auxiliary Instance", "h": "rcmtspit.htm#BRADV89797", 
 "c": [ { "t": "Renaming TSPITR Recovery Set Data Files with SET NEWNAME", "h": "rcmtspit.htm#BRADV89799" },
 { "t": "Naming TSPITR Auxiliary Set Data Files", "h": "rcmtspit.htm#BRADV89800" },
 { "t": "Using Image Copies for Faster RMAN TSPITR Performance", "h": "rcmtspit.htm#BRADV89805" },
 { "t": "Customizing Initialization Parameters for the Automatic Auxiliary Instance in TSPITR", "h": "rcmtspit.htm#BRADV89809" },
 { }
 ]
 },
{ "a": "e10642idm140591990136768", "t": "Performing RMAN TSPITR Using Your Own Auxiliary Instance", "h": "rcmtspit.htm#BRADV89812", 
 "c": [ { "t": "Preparing Your Own Auxiliary Instance for RMAN TSPITR", "h": "rcmtspit.htm#BRADV89813" },
 { "t": "Preparing RMAN Commands for TSPITR with Your Own Auxiliary Instance", "h": "rcmtspit.htm#BRADV89817" },
 { "t": "Executing TSPITR with Your Own Auxiliary Instance", "h": "rcmtspit.htm#BRADV89820" },
 { "t": "Performing TSPITR with Your Own Auxiliary Instance: Scenario", "h": "rcmtspit.htm#BRADV89825" },
 { }
 ]
 },
{ "a": "e10642idm140592096221840", "t": "Troubleshooting RMAN TSPITR", "h": "rcmtspit.htm#BRADV99978", 
 "c": [ { "t": "Troubleshooting Filename Conflicts", "h": "rcmtspit.htm#BRADV89826" },
 { "t": "Troubleshooting the Identification of Tablespaces with Undo Segments", "h": "rcmtspit.htm#BRADV89827" },
 { "t": "Troubleshooting the Restart of a Manual Auxiliary Instance After TSPITR Failure", "h": "rcmtspit.htm#BRADV89828" },
 { }
 ]
 },
 { }
 ]
 },
{ "a": "e10642idm140592020753344", "t": "Tuning RMAN Performance", "h": "rcmtunin.htm#BRADV011", 
 "c": [ { "t": "Purpose of RMAN Performance Tuning", "h": "rcmtunin.htm#BRADV89842" },
{ "a": "e10642idm140591947130256", "t": "Basic Concepts of RMAN Performance Tuning", "h": "rcmtunin.htm#BRADV170", 
 "c": [ { "t": "Read Phase", "h": "rcmtunin.htm#BRADV90067" },
 { "t": "Copy Phase", "h": "rcmtunin.htm#BRADV90071" },
 { "t": "Write Phase for System Backup Tape (SBT)", "h": "rcmtunin.htm#BRADV90072" },
 { "t": "Write Phase for Disk", "h": "rcmtunin.htm#BRADV90075" },
 { }
 ]
 },
{ "a": "e10642idm140592011337344", "t": "Using V$ Views to Diagnose RMAN Performance Problems", "h": "rcmtunin.htm#BRADV90076", 
 "c": [ { "t": "Monitoring RMAN Job Progress with V$SESSION_LONGOPS", "h": "rcmtunin.htm#BRADV99981" },
 { "t": "Identifying Bottlenecks with V$BACKUP_SYNC_IO and V$BACKUP_ASYNC_IO", "h": "rcmtunin.htm#BRADV89862" },
 { }
 ]
 },
{ "a": "e10642idm140592093343360", "t": "Tuning RMAN Backup Performance", "h": "rcmtunin.htm#BRADV172", 
 "c": [ { "t": "Step 1: Remove the RATE Parameter from Channel Settings", "h": "rcmtunin.htm#BRADV89855" },
 { "t": "Step 2: If You Use Synchronous Disk I/O, Set DBWR_IO_SLAVES", "h": "rcmtunin.htm#BRADV89856" },
 { "t": "Step 3: If You Fail to Allocate Shared Memory, Set LARGE_POOL_SIZE", "h": "rcmtunin.htm#BRADV89857" },
 { "t": "Step 4: Tune the Read, Write, and Copy Phases", "h": "rcmtunin.htm#BRADV89858" },
 { }
 ]
 },
 { }
 ]
 },
{ "a": "e10642idm140592006380464", "t": "Troubleshooting RMAN Operations", "h": "rcmtroub.htm#BRADV012", 
 "c": [{ "a": "e10642idm140591991968896", "t": "Interpreting RMAN Message Output", "h": "rcmtroub.htm#BRADV174", 
 "c": [ { "t": "Identifying Types of Message Output", "h": "rcmtroub.htm#BRADV89865" },
 { "t": "Recognizing RMAN Error Message Stacks", "h": "rcmtroub.htm#BRADV89866" },
 { "t": "Identifying Error Codes", "h": "rcmtroub.htm#BRADV89867" },
 { "t": "Interpreting RMAN Error Stacks", "h": "rcmtroub.htm#BRADV89870" },
 { "t": "Identifying RMAN Return Codes", "h": "rcmtroub.htm#BRADV89875" },
 { }
 ]
 },
{ "a": "e10642idm140592001661360", "t": "Using V$ Views for RMAN Troubleshooting", "h": "rcmtroub.htm#BRADV177", 
 "c": [ { "t": "Monitoring RMAN Interaction with the Media Manager", "h": "rcmtroub.htm#BRADV89876" },
 { "t": "Correlating Server Sessions with RMAN Channels", "h": "rcmtroub.htm#BRADV89877" },
 { }
 ]
 },
{ "a": "e10642idm140591984096512", "t": "Testing the Media Management API", "h": "rcmtroub.htm#BRADV175", 
 "c": [ { "t": "Obtaining the sbttest Utility", "h": "rcmtroub.htm#BRADV89882" },
 { "t": "Obtaining Online Documentation for the sbttest Utility", "h": "rcmtroub.htm#BRADV89883" },
 { "t": "Using the sbttest Utility", "h": "rcmtroub.htm#BRADV89884" },
 { }
 ]
 },
{ "a": "e10642idm140591986476736", "t": "Terminating an RMAN Command", "h": "rcmtroub.htm#BRADV176", 
 "c": [ { "t": "Terminating the Session with ALTER SYSTEM KILL SESSION", "h": "rcmtroub.htm#BRADV89885" },
 { "t": "Terminating the Session at the Operating System Level", "h": "rcmtroub.htm#BRADV89886" },
 { "t": "Terminating an RMAN Session That Is Not Responding in the Media Manager", "h": "rcmtroub.htm#BRADV89887" },
 { }
 ]
 },
 { }
 ]
 },
{ "a": "e10642idm140592048263408", "t": "Duplicating a Database", "h": "rcmdupdb.htm#BRADV010", 
 "c": [{ "a": "e10642idm140591997423920", "t": "Overview of RMAN Database Duplication", "h": "rcmdupdb.htm#BRADV89927", 
 "c": [ { "t": "Purpose of Database Duplication", "h": "rcmdupdb.htm#BRADV89928" },
 { "t": "Basic Concepts of Database Duplication", "h": "rcmdupdb.htm#BRADV89929" },
 { "t": "Basic Steps of Database Duplication", "h": "rcmdupdb.htm#BRADV89930" },
 { }
 ]
 },
{ "a": "e10642idm140592016674832", "t": "Preparing to Duplicate a Database", "h": "rcmdupdb.htm#BRADV426", 
 "c": [ { "t": "Step 1: Choosing a Duplication Technique", "h": "rcmdupdb.htm#BRADV427" },
 { "t": "Step 2: Choosing a Strategy for Naming Duplicate Files", "h": "rcmdupdb.htm#BRADV298" },
 { "t": "Step 3: Making Backups Accessible to the Duplicate Instance", "h": "rcmdupdb.htm#BRADV89931" },
 { "t": "Step 4: Preparing Remote Access to Databases", "h": "rcmdupdb.htm#BRADV533" },
 { "t": "Step 5: Creating an Initialization Parameter File and Starting the Auxiliary Instance", "h": "rcmdupdb.htm#BRADV167" },
 { }
 ]
 },
 { "t": "Placing the Source Database in the Proper State", "h": "rcmdupdb.htm#BRADV430" },
 { "t": "Starting RMAN and Connecting to Databases", "h": "rcmdupdb.htm#BRADV299" },
{ "a": "e10642idm140591942168512", "t": "Configuring RMAN Channels for Use in Duplication", "h": "rcmdupdb.htm#BRADV89938", 
 "c": [ { "t": "Configuring Channels for Active Database Duplication", "h": "rcmdupdb.htm#BRADV431" },
 { "t": "Configuring Channels for Backup-Based Duplication", "h": "rcmdupdb.htm#BRADV432" },
 { }
 ]
 },
{ "a": "e10642idm140592097119776", "t": "Duplicating a Database", "h": "rcmdupdb.htm#BRADV168", 
 "c": [ { "t": "Backup-Based Duplication Without a Target Connection: Example", "h": "rcmdupdb.htm#BRADV435" },
 { "t": "Backup-Based Duplication with a Target Connection: Example", "h": "rcmdupdb.htm#BRADV438" },
 { "t": "Backup-Based Duplication Without a Target and a Recovery Catalog Connection: Example", "h": "rcmdupdb.htm#BRADV538" },
 { }
 ]
 },
 { "t": "Restarting DUPLICATE After a Failure", "h": "rcmdupdb.htm#BRADV440" },
 { }
 ]
 },
{ "a": "e10642idm140592080265632", "t": "Duplicating a Database: Advanced Topics", "h": "rcmdupad.htm#BRADV441", 
 "c": [{ "a": "e10642idm140592006423664", "t": "Specifying Alternative Names for Duplicate Database Files", "h": "rcmdupad.htm#BRADV442", 
 "c": [ { "t": "Specifying Non-OMF or Non-ASM Alternative Names for Duplicate Database Files", "h": "rcmdupad.htm#BRADV443" },
 { "t": "Specifying OMF or ASM Alternative Names for Duplicate Database Files", "h": "rcmdupad.htm#BRADV448" },
 { }
 ]
 },
 { "t": "Making Disk Backups Accessible Without Shared Disk", "h": "rcmdupad.htm#BRADV99994" },
 { "t": "Duplicating a Database When No Server Parameter File Exists", "h": "rcmdupad.htm#BRADV454" },
 { "t": "Starting the Auxiliary Instance When No Server Parameter File Exists", "h": "rcmdupad.htm#BRADV457" },
{ "a": "e10642idm140591998442048", "t": "Duplicating a Subset of the Source Database Tablespaces", "h": "rcmdupad.htm#BRADV89951", 
 "c": [ { "t": "Excluding Specified Tablespaces", "h": "rcmdupad.htm#BRADV89952" },
 { "t": "Including Specified Tablespaces", "h": "rcmdupad.htm#BRADV89954" },
 { }
 ]
 },
 { }
 ]
 },
{ "a": "e10642idm140591977099328", "t": "Creating Transportable Tablespace Sets", "h": "rcmttbsb.htm#BRADV05141", 
 "c": [{ "a": "e10642idm140591999002464", "t": "Overview of Creating Transportable Tablespace Sets", "h": "rcmttbsb.htm#BRADV89959", 
 "c": [ { "t": "Purpose of Creating Transportable Tablespace Sets", "h": "rcmttbsb.htm#BRADV89960" },
 { "t": "Basic Concepts of Transportable Tablespace Sets", "h": "rcmttbsb.htm#BRADV89961" },
 { "t": "Basic Steps of Creating Transportable Tablespace Sets", "h": "rcmttbsb.htm#BRADV89962" },
 { }
 ]
 },
{ "a": "e10642idm140591958089248", "t": "Customizing Initialization Parameters for the Auxiliary Instance", "h": "rcmttbsb.htm#BRADV89963", 
 "c": [ { "t": "Setting Initialization Parameters for the Auxiliary Instance", "h": "rcmttbsb.htm#BRADV89964" },
 { "t": "Setting the Location of the Auxiliary Instance Parameter File", "h": "rcmttbsb.htm#BRADV89965" },
 { }
 ]
 },
 { "t": "Creating a Transportable Tablespace Set", "h": "rcmttbsb.htm#BRADV89966" },
 { "t": "Troubleshooting the Creation of Transportable Tablespace Sets", "h": "rcmttbsb.htm#BRADV89967" },
{ "a": "e10642idm140591975586240", "t": "Transportable Tablespace Set Scenarios", "h": "rcmttbsb.htm#BRADV89968", 
 "c": [ { "t": "Creating a Transportable Tablespace Set at a Specified Time or SCN", "h": "rcmttbsb.htm#BRADV89969" },
 { "t": "Specifying Locations for Data Pump Files", "h": "rcmttbsb.htm#BRADV89970" },
 { "t": "Specifying Auxiliary File Locations", "h": "rcmttbsb.htm#BRADV39711" },
 { }
 ]
 },
 { }
 ]
 },
{ "a": "e10642idm140592089775008", "t": "Transporting Data Across Platforms", "h": "rcmxplat.htm#BRADV05432", 
 "c": [{ "a": "e10642idm140592017092656", "t": "Overview of Cross-Platform Data Transportation", "h": "rcmxplat.htm#BRADV89977", 
 "c": [ { "t": "Purpose of Cross-Platform Data Transportation", "h": "rcmxplat.htm#BRADV89978" },
 { "t": "Basic Concepts of Cross-Platform Data Transportation", "h": "rcmxplat.htm#BRADV89979" },
 { }
 ]
 },
 { "t": "Performing Cross-Platform Tablespace Conversion on the Source Host", "h": "rcmxplat.htm#BRADV89982" },
{ "a": "e10642idm140592065015168", "t": "Performing Cross-Platform Data File Conversion on the Destination Host", "h": "rcmxplat.htm#BRADV89983", 
 "c": [ { "t": "About Cross-Platform Data File Conversion on the Destination Host", "h": "rcmxplat.htm#BRADV89984" },
 { "t": "Using CONVERT DATAFILE to Convert Data File Formats", "h": "rcmxplat.htm#BRADV89985" },
 { }
 ]
 },
 { "t": "Checking the Database Before Cross-Platform Database Conversion", "h": "rcmxplat.htm#BRADV89986" },
 { "t": "Converting Data Files on the Source Host When Transporting a Database", "h": "rcmxplat.htm#BRADV89987" },
{ "a": "e10642idm140592021274704", "t": "Converting Data Files on the Destination Host When Transporting a Database", "h": "rcmxplat.htm#BRADV89988", 
 "c": [ { "t": "Performing Preliminary Data File Conversion Steps on the Source Host", "h": "rcmxplat.htm#BRADV89989" },
 { "t": "Converting Data Files on the Destination Host", "h": "rcmxplat.htm#BRADV89990" },
 { }
 ]
 },
 { }
 ]
 },
{ "a": "e10642idm140592019098352", "t": "Making User-Managed Database Backups", "h": "osbackup.htm#BRADV016", 
 "c": [{ "a": "e10642idm140592018495296", "t": "Querying V$ Views to Obtain Backup Information", "h": "osbackup.htm#BRADV198", 
 "c": [ { "t": "Listing Database Files Before a Backup", "h": "osbackup.htm#BRADV89998" },
 { "t": "Determining Data File Status for Online Tablespace Backups", "h": "osbackup.htm#BRADV89999" },
 { }
 ]
 },
 { "t": "Making User-Managed Backups of the Whole Database", "h": "osbackup.htm#BRADV199" },
{ "a": "e10642idm140591948319504", "t": "Making User-Managed Backups of Tablespaces and Data Files", "h": "osbackup.htm#BRADV90001", 
 "c": [ { "t": "Making User-Managed Backups of Offline Tablespaces and Data Files", "h": "osbackup.htm#BRADV20033" },
 { "t": "Making User-Managed Backups of Online Tablespaces and Data Files", "h": "osbackup.htm#BRADV201" },
 { }
 ]
 },
{ "a": "e10642idm140592009003904", "t": "Making User-Managed Backups of the Control File", "h": "osbackup.htm#BRADV202", 
 "c": [ { "t": "Backing Up the Control File to a Binary File", "h": "osbackup.htm#BRADV90010" },
 { "t": "Backing Up the Control File to a Trace File", "h": "osbackup.htm#BRADV90011" },
 { }
 ]
 },
 { "t": "Making User-Managed Backups of Archived Redo Logs", "h": "osbackup.htm#BRADV20333" },
{ "a": "e10642idm140592090134880", "t": "Making User-Managed Backups in SUSPEND Mode", "h": "osbackup.htm#BRADV204", 
 "c": [ { "t": "About the Suspend/Resume Feature", "h": "osbackup.htm#BRADV90012" },
 { "t": "Making Backups in a Suspended Database", "h": "osbackup.htm#BRADV90013" },
 { }
 ]
 },
{ "a": "e10642idm140591993643424", "t": "Making User-Managed Backups to Raw Devices", "h": "osbackup.htm#BRADV205", 
 "c": [ { "t": "Backing Up to Raw Devices on Linux and UNIX", "h": "osbackup.htm#BRADV90014" },
 { "t": "Backing Up to Raw Devices on Windows", "h": "osbackup.htm#BRADV90016" },
 { }
 ]
 },
 { "t": "Making Backups with the Volume Shadow Copy Service (VSS)", "h": "osbackup.htm#BRADV90019" },
{ "a": "e10642idm140592039632640", "t": "Verifying User-Managed Data File Backups", "h": "osbackup.htm#BRADV206", 
 "c": [ { "t": "Testing the Restoration of Data File Backups", "h": "osbackup.htm#BRADV90020" },
 { "t": "Running the DBVERIFY Utility", "h": "osbackup.htm#BRADV90021" },
 { }
 ]
 },
 { }
 ]
 },
{ "a": "e10642idm140591958360832", "t": "Performing User-Managed Database Flashback and Recovery", "h": "osrecvry.htm#BRADV017", 
 "c": [ { "t": "Performing Flashback Database with SQL*Plus", "h": "osrecvry.htm#BRADV99982" },
{ "a": "e10642idm140591961543808", "t": "Overview of User-Managed Media Recovery", "h": "osrecvry.htm#BRADV215", 
 "c": [ { "t": "About User-Managed Restore and Recovery", "h": "osrecvry.htm#BRADV210" },
 { "t": "Automatic Recovery with the RECOVER Command", "h": "osrecvry.htm#BRADV90025" },
 { "t": "Recovery When Archived Logs Are in the Default Location", "h": "osrecvry.htm#BRADV90028" },
 { "t": "Recovery When Archived Logs Are in a Nondefault Location", "h": "osrecvry.htm#BRADV90029" },
 { "t": "Recovery Cancellation", "h": "osrecvry.htm#BRADV99983" },
 { "t": "Parallel Media Recovery", "h": "osrecvry.htm#BRADV221" },
 { }
 ]
 },
{ "a": "e10642idm140591983721344", "t": "Performing Complete Database Recovery", "h": "osrecvry.htm#BRADV216", 
 "c": [ { "t": "Performing Closed Database Recovery", "h": "osrecvry.htm#BRADV90032" },
 { "t": "Performing Open Database Recovery", "h": "osrecvry.htm#BRADV90033" },
 { }
 ]
 },
{ "a": "e10642idm140591986390496", "t": "Performing Incomplete Database Recovery", "h": "osrecvry.htm#BRADV217", 
 "c": [ { "t": "Performing Cancel-Based Incomplete Recovery", "h": "osrecvry.htm#BRADV90034" },
 { "t": "Performing Time-Based or Change-Based Incomplete Recovery", "h": "osrecvry.htm#BRADV90035" },
 { }
 ]
 },
 { "t": "Recovering a Database in NOARCHIVELOG Mode", "h": "osrecvry.htm#BRADV219" },
{ "a": "e10642idm140591975629264", "t": "Troubleshooting Media Recovery", "h": "osrecvry.htm#BRADV90036", 
 "c": [ { "t": "About User-Managed Media Recovery Problems", "h": "osrecvry.htm#BRADV241" },
 { "t": "Investigating the Media Recovery Problem: Phase 1", "h": "osrecvry.htm#BRADV242" },
 { "t": "Trying to Fix the Recovery Problem Without Corrupting Blocks: Phase 2", "h": "osrecvry.htm#BRADV24383" },
 { "t": "Deciding Whether to Allow Recovery to Mark as Corrupt Blocks: Phase 3", "h": "osrecvry.htm#BRADV99984" },
 { "t": "Allowing Recovery to Corrupt Blocks: Phase 4", "h": "osrecvry.htm#BRADV244" },
 { "t": "Performing Trial Recovery", "h": "osrecvry.htm#BRADV245" },
 { }
 ]
 },
 { }
 ]
 },
{ "a": "e10642idm140591990007808", "t": "Performing User-Managed Recovery: Advanced Scenarios", "h": "osadvsce.htm#BRADV018", 
 "c": [{ "a": "e10642idm140592008314544", "t": "Responding to the Loss of a Subset of the Current Control Files", "h": "osadvsce.htm#BRADV90039", 
 "c": [ { "t": "Copying a Multiplexed Control File to a Default Location", "h": "osadvsce.htm#BRADV90040" },
 { "t": "Copying a Multiplexed Control File to a Nondefault Location", "h": "osadvsce.htm#BRADV90041" },
 { }
 ]
 },
{ "a": "e10642idm140592092968192", "t": "Recovering After the Loss of All Current Control Files", "h": "osadvsce.htm#BRADV90042", 
 "c": [ { "t": "Recovering with a Backup Control File in the Default Location", "h": "osadvsce.htm#BRADV90043" },
 { "t": "Recovering with a Backup Control File in a Nondefault Location", "h": "osadvsce.htm#BRADV90044" },
 { "t": "Recovering Through an Added Data File with a Backup Control File", "h": "osadvsce.htm#BRADV223" },
 { "t": "Recovering Read-Only Tablespaces with a Backup Control File", "h": "osadvsce.htm#BRADV227" },
 { }
 ]
 },
{ "a": "e10642idm140592086178912", "t": "Re-Creating a Control File", "h": "osadvsce.htm#BRADV90045", 
 "c": [ { "t": "Recovering Through a RESETLOGS with a Created Control File", "h": "osadvsce.htm#BRADV225" },
 { "t": "Recovery of Read-Only Files with a Re-Created Control File", "h": "osadvsce.htm#BRADV90046" },
 { }
 ]
 },
 { "t": "Re-Creating Data Files When Backups Are Unavailable", "h": "osadvsce.htm#BRADV224" },
 { "t": "Recovering NOLOGGING Tables and Indexes", "h": "osadvsce.htm#BRADV90047" },
 { "t": "Recovering Transportable Tablespaces", "h": "osadvsce.htm#BRADV228" },
{ "a": "e10642idm140592070946288", "t": "Recovering After the Loss of Online Redo Log Files", "h": "osadvsce.htm#BRADV229", 
 "c": [ { "t": "Recovering After Losing a Member of a Multiplexed Online Redo Log Group", "h": "osadvsce.htm#BRADV90048" },
 { "t": "Recovering After Losing All Members of an Online Redo Log Group", "h": "osadvsce.htm#BRADV90049" },
 { }
 ]
 },
 { "t": "Recovering from a Dropped Table Without Using Flashback Features", "h": "osadvsce.htm#BRADV99985" },
 { "t": "Dropping a Database with SQL*Plus", "h": "osadvsce.htm#BRADV233" },
 { }
 ]
 },
 { "t": "Glossary", "h": "glossary.htm#BRADV526" },
  { }
 ] } ]}